{"inputs":[{"name":".clientdata_pixelratio","timestamp":"2019-08-05T20:35:36-04:00","value":2.625,"type":"","binding":""},{"name":".clientdata_output_bar_width","timestamp":"2019-08-05T20:30:24-04:00","value":382,"type":"","binding":""},{"name":".clientdata_pixelratio","timestamp":"2019-08-05T20:33:00-04:00","value":2.625,"type":"","binding":""},{"name":".clientdata_output_bar_width","timestamp":"2019-08-05T20:31:00-04:00","value":382,"type":"","binding":""},{"name":".clientdata_pixelratio","timestamp":"2019-08-05T20:31:53-04:00","value":2.625,"type":"","binding":""},{"name":".clientdata_pixelratio","timestamp":"2019-08-05T20:34:07-04:00","value":2.625,"type":"","binding":""},{"name":".clientdata_pixelratio","timestamp":"2019-08-05T20:30:36-04:00","value":2.625,"type":"","binding":""},{"name":".clientdata_output_bar_width","timestamp":"2019-08-05T20:35:29-04:00","value":382,"type":"","binding":""},{"name":".clientdata_output_bar_width","timestamp":"2019-08-05T20:34:07-04:00","value":382,"type":"","binding":""},{"name":".clientdata_pixelratio","timestamp":"2019-08-05T20:35:37-04:00","value":2.625,"type":"","binding":""},{"name":".clientdata_pixelratio","timestamp":"2019-08-05T20:34:57-04:00","value":2.625,"type":"","binding":""},{"name":".clientdata_pixelratio","timestamp":"2019-08-05T20:31:54-04:00","value":2.625,"type":"","binding":""},{"name":"slider1","timestamp":"2019-08-05T20:36:20-04:00","value":-0.022,"type":"","binding":"shiny.sliderInput"},{"name":".clientdata_output_bar_width","timestamp":"2019-08-05T20:35:18-04:00","value":382,"type":"","binding":""},{"name":".clientdata_pixelratio","timestamp":"2019-08-05T20:34:51-04:00","value":2.625,"type":"","binding":""},{"name":".clientdata_output_bar_width","timestamp":"2019-08-05T20:30:28-04:00","value":382,"type":"","binding":""},{"name":".clientdata_pixelratio","timestamp":"2019-08-05T20:30:54-04:00","value":2.625,"type":"","binding":""},{"name":".clientdata_output_bar_height","timestamp":"2019-08-05T20:33:39-04:00","value":400,"type":"","binding":""},{"name":"sideA","timestamp":"2019-08-05T20:36:04-04:00","value":["Startup Pick 1.05 | Ezekiel Elliott","Startup Pick 3.05 | Dalvin Cook"],"type":"","binding":"shiny.selectInput"},{"name":".clientdata_output_bar_width","timestamp":"2019-08-05T20:34:00-04:00","value":382,"type":"","binding":""},{"name":".clientdata_output_bar_height","timestamp":"2019-08-05T20:34:22-04:00","value":400,"type":"","binding":""},{"name":".clientdata_pixelratio","timestamp":"2019-08-05T20:30:45-04:00","value":2.625,"type":"","binding":""},{"name":"sideB","timestamp":"2019-08-05T20:33:35-04:00","value":{},"type":"","binding":"shiny.selectInput"},{"name":".clientdata_pixelratio","timestamp":"2019-08-05T20:32:42-04:00","value":2.625,"type":"","binding":""},{"name":".clientdata_output_bar_width","timestamp":"2019-08-05T20:33:39-04:00","value":382,"type":"","binding":""},{"name":".clientdata_output_bar_width","timestamp":"2019-08-05T20:33:32-04:00","value":382,"type":"","binding":""},{"name":".clientdata_output_bar_height","timestamp":"2019-08-05T20:30:37-04:00","value":400,"type":"","binding":""},{"name":"calcType","timestamp":"2019-08-05T20:33:35-04:00","value":"postdraft","type":"","binding":"shiny.radioGroupButtonsInput"},{"name":".clientdata_pixelratio","timestamp":"2019-08-05T20:36:09-04:00","value":2.625,"type":"","binding":""},{"name":".clientdata_output_bar_height","timestamp":"2019-08-05T20:32:45-04:00","value":400,"type":"","binding":""},{"name":".clientdata_output_bar_width","timestamp":"2019-08-05T20:30:53-04:00","value":382,"type":"","binding":""},{"name":"sideB","timestamp":"2019-08-05T20:30:31-04:00","value":["Baker Mayfield"],"type":"","binding":"shiny.selectInput"},{"name":".clientdata_pixelratio","timestamp":"2019-08-05T20:34:31-04:00","value":2.625,"type":"","binding":""},{"name":".clientdata_output_bar_height","timestamp":"2019-08-05T20:31:55-04:00","value":400,"type":"","binding":""},{"name":".clientdata_output_bar_width","timestamp":"2019-08-05T20:36:19-04:00","value":382,"type":"","binding":""},{"name":".clientdata_output_bar_height","timestamp":"2019-08-05T20:36:17-04:00","value":400,"type":"","binding":""},{"name":".clientdata_output_bar_height","timestamp":"2019-08-05T20:34:53-04:00","value":400,"type":"","binding":""},{"name":".clientdata_output_bar_height","timestamp":"2019-08-05T20:36:01-04:00","value":400,"type":"","binding":""},{"name":".clientdata_output_bar_width","timestamp":"2019-08-05T20:33:33-04:00","value":382,"type":"","binding":""},{"name":".clientdata_output_bar_height","timestamp":"2019-08-05T20:36:23-04:00","value":400,"type":"","binding":""},{"name":".clientdata_output_bar_height","timestamp":"2019-08-05T20:34:51-04:00","value":400,"type":"","binding":""},{"name":".clientdata_output_bar_width","timestamp":"2019-08-05T20:35:09-04:00","value":382,"type":"","binding":""},{"name":"sideB","timestamp":"2019-08-05T20:30:58-04:00","value":["Baker Mayfield","Alvin Kamara"],"type":"","binding":"shiny.selectInput"},{"name":".clientdata_output_bar_height","timestamp":"2019-08-05T20:34:23-04:00","value":400,"type":"","binding":""},{"name":"sideA","timestamp":"2019-08-05T20:30:24-04:00","value":["Patrick Mahomes"],"type":"","binding":"shiny.selectInput"},{"name":".clientdata_output_bar_width","timestamp":"2019-08-05T20:30:45-04:00","value":382,"type":"","binding":""},{"name":".clientdata_output_bar_height","timestamp":"2019-08-05T20:34:00-04:00","value":400,"type":"","binding":""},{"name":"sideB","timestamp":"2019-08-05T20:33:59-04:00","value":["Startup Pick 1.09 | Baker Mayfield"],"type":"","binding":"shiny.selectInput"},{"name":".clientdata_output_bar_width","timestamp":"2019-08-05T20:35:47-04:00","value":382,"type":"","binding":""},{"name":".clientdata_output_bar_width","timestamp":"2019-08-05T20:31:43-04:00","value":382,"type":"","binding":""},{"name":".clientdata_pixelratio","timestamp":"2019-08-05T20:31:57-04:00","value":2.625,"type":"","binding":""},{"name":".clientdata_output_bar_height","timestamp":"2019-08-05T20:33:40-04:00","value":400,"type":"","binding":""},{"name":"sideA","timestamp":"2019-08-05T20:36:01-04:00","value":["Startup Pick 1.05 | Ezekiel Elliott","Startup Pick 3.05 | Dalvin Cook"],"type":"","binding":"shiny.selectInput"},{"name":".clientdata_output_bar_width","timestamp":"2019-08-05T20:34:09-04:00","value":382,"type":"","binding":""},{"name":".clientdata_output_bar_height","timestamp":"2019-08-05T20:33:55-04:00","value":400,"type":"","binding":""},{"name":".clientdata_output_bar_width","timestamp":"2019-08-05T20:30:42-04:00","value":382,"type":"","binding":""},{"name":".clientdata_output_bar_width","timestamp":"2019-08-05T20:34:39-04:00","value":382,"type":"","binding":""},{"name":"sideA","timestamp":"2019-08-05T20:33:37-04:00","value":["2020 1st"],"type":"","binding":"shiny.selectInput"},{"name":".clientdata_output_bar_height","timestamp":"2019-08-05T20:31:54-04:00","value":400,"type":"","binding":""},{"name":".clientdata_output_bar_height","timestamp":"2019-08-05T20:33:56-04:00","value":400,"type":"","binding":""},{"name":".clientdata_pixelratio","timestamp":"2019-08-05T20:32:48-04:00","value":2.625,"type":"","binding":""},{"name":"sideB","timestamp":"2019-08-05T20:34:20-04:00","value":["Startup Pick 1.09 | Baker Mayfield","Startup Pick 3.05 | Dalvin Cook"],"type":"","binding":"shiny.selectInput"},{"name":"sideB","timestamp":"2019-08-05T20:36:23-04:00","value":["Startup Pick 1.09 | Baker Mayfield","Startup Pick 2.02 | Michael Thomas"],"type":"","binding":"shiny.selectInput"},{"name":".clientdata_output_bar_height","timestamp":"2019-08-05T20:34:24-04:00","value":400,"type":"","binding":""},{"name":"sideA","timestamp":"2019-08-05T20:36:22-04:00","value":["Startup Pick 1.05 | Ezekiel Elliott","Startup Pick 3.05 | Dalvin Cook"],"type":"","binding":"shiny.selectInput"},{"name":"calcType","timestamp":"2019-08-05T20:33:31-04:00","value":"postdraft","type":"","binding":"shiny.radioGroupButtonsInput"},{"name":".clientdata_output_bar_height","timestamp":"2019-08-05T20:36:28-04:00","value":400,"type":"","binding":""},{"name":"sideB","timestamp":"2019-08-05T20:36:01-04:00","value":["Startup Pick 1.09 | Baker Mayfield","Startup Pick 2.02 | Michael Thomas"],"type":"","binding":"shiny.selectInput"},{"name":"sideA","timestamp":"2019-08-05T20:33:32-04:00","value":["2020 1st"],"type":"","binding":"shiny.selectInput"},{"name":".clientdata_output_bar_height","timestamp":"2019-08-05T20:36:18-04:00","value":400,"type":"","binding":""},{"name":".clientdata_output_bar_width","timestamp":"2019-08-05T20:34:23-04:00","value":382,"type":"","binding":""},{"name":".clientdata_output_bar_height","timestamp":"2019-08-05T20:32:41-04:00","value":400,"type":"","binding":""},{"name":".clientdata_output_bar_width","timestamp":"2019-08-05T20:31:46-04:00","value":382,"type":"","binding":""},{"name":"sideA","timestamp":"2019-08-05T20:36:24-04:00","value":["Startup Pick 1.05 | Ezekiel Elliott","Startup Pick 3.05 | Dalvin Cook"],"type":"","binding":"shiny.selectInput"},{"name":".clientdata_output_bar_width","timestamp":"2019-08-05T20:36:18-04:00","value":382,"type":"","binding":""},{"name":".clientdata_pixelratio","timestamp":"2019-08-05T20:36:28-04:00","value":2.625,"type":"","binding":""},{"name":".clientdata_output_bar_width","timestamp":"2019-08-05T20:33:55-04:00","value":382,"type":"","binding":""},{"name":".clientdata_output_bar_width","timestamp":"2019-08-05T20:31:02-04:00","value":382,"type":"","binding":""},{"name":"slider2","timestamp":"2019-08-05T20:36:01-04:00","value":0.5,"type":"","binding":"shiny.sliderInput"},{"name":".clientdata_output_bar_width","timestamp":"2019-08-05T20:34:51-04:00","value":382,"type":"","binding":""},{"name":".clientdata_output_bar_height","timestamp":"2019-08-05T20:31:04-04:00","value":400,"type":"","binding":""},{"name":".clientdata_pixelratio","timestamp":"2019-08-05T20:35:53-04:00","value":2.625,"type":"","binding":""},{"name":".clientdata_output_bar_width","timestamp":"2019-08-05T20:34:58-04:00","value":382,"type":"","binding":""},{"name":"leagueSize","timestamp":"2019-08-05T20:33:40-04:00","value":"10","type":"","binding":"shiny.selectInput"},{"name":".clientdata_output_bar_width","timestamp":"2019-08-05T20:32:33-04:00","value":382,"type":"","binding":""},{"name":".clientdata_output_bar_height","timestamp":"2019-08-05T20:36:03-04:00","value":400,"type":"","binding":""},{"name":"sideB","timestamp":"2019-08-05T20:36:01-04:00","value":["Startup Pick 1.09 | Baker Mayfield","Startup Pick 2.02 | Michael Thomas"],"type":"","binding":"shiny.selectInput"},{"name":".clientdata_pixelratio","timestamp":"2019-08-05T20:32:44-04:00","value":2.625,"type":"","binding":""},{"name":"sideB","timestamp":"2019-08-05T20:36:03-04:00","value":["Startup Pick 1.09 | Baker Mayfield","Startup Pick 2.02 | Michael Thomas"],"type":"","binding":"shiny.selectInput"},{"name":".clientdata_output_bar_width","timestamp":"2019-08-05T20:30:37-04:00","value":382,"type":"","binding":""},{"name":".clientdata_output_bar_width","timestamp":"2019-08-05T20:33:35-04:00","value":382,"type":"","binding":""},{"name":"sideB","timestamp":"2019-08-05T20:33:36-04:00","value":{},"type":"","binding":"shiny.selectInput"},{"name":".clientdata_output_bar_height","timestamp":"2019-08-05T20:31:57-04:00","value":400,"type":"","binding":""},{"name":".clientdata_output_bar_width","timestamp":"2019-08-05T20:35:30-04:00","value":382,"type":"","binding":""},{"name":".clientdata_output_bar_height","timestamp":"2019-08-05T20:34:15-04:00","value":400,"type":"","binding":""},{"name":".clientdata_pixelratio","timestamp":"2019-08-05T20:31:47-04:00","value":2.625,"type":"","binding":""},{"name":"slider2","timestamp":"2019-08-05T20:36:00-04:00","value":0.5,"type":"","binding":"shiny.sliderInput"},{"name":".clientdata_output_bar_width","timestamp":"2019-08-05T20:33:41-04:00","value":382,"type":"","binding":""},{"name":".clientdata_output_bar_height","timestamp":"2019-08-05T20:34:45-04:00","value":400,"type":"","binding":""},{"name":".clientdata_output_bar_width","timestamp":"2019-08-05T20:35:48-04:00","value":382,"type":"","binding":""},{"name":".clientdata_pixelratio","timestamp":"2019-08-05T20:30:18-04:00","value":2.625,"type":"","binding":""},{"name":".clientdata_output_bar_height","timestamp":"2019-08-05T20:34:09-04:00","value":400,"type":"","binding":""},{"name":".clientdata_pixelratio","timestamp":"2019-08-05T20:34:00-04:00","value":2.625,"type":"","binding":""},{"name":".clientdata_output_bar_height","timestamp":"2019-08-05T20:34:43-04:00","value":400,"type":"","binding":""},{"name":".clientdata_output_bar_width","timestamp":"2019-08-05T20:33:38-04:00","value":382,"type":"","binding":""},{"name":".clientdata_pixelratio","timestamp":"2019-08-05T20:31:27-04:00","value":2.625,"type":"","binding":""},{"name":".clientdata_output_bar_height","timestamp":"2019-08-05T20:35:18-04:00","value":400,"type":"","binding":""},{"name":"sideA","timestamp":"2019-08-05T20:33:27-04:00","value":["Patrick Mahomes","LeVeon Bell","2020 1st","Evan Engram"],"type":"","binding":"shiny.selectInput"},{"name":"sideB","timestamp":"2019-08-05T20:36:18-04:00","value":["Startup Pick 1.09 | Baker Mayfield","Startup Pick 2.02 | Michael Thomas"],"type":"","binding":"shiny.selectInput"},{"name":".clientdata_output_bar_height","timestamp":"2019-08-05T20:34:51-04:00","value":400,"type":"","binding":""},{"name":".clientdata_pixelratio","timestamp":"2019-08-05T20:34:41-04:00","value":2.625,"type":"","binding":""},{"name":".clientdata_output_bar_height","timestamp":"2019-08-05T20:32:56-04:00","value":400,"type":"","binding":""},{"name":".clientdata_output_bar_height","timestamp":"2019-08-05T20:30:51-04:00","value":400,"type":"","binding":""},{"name":".clientdata_output_bar_height","timestamp":"2019-08-05T20:30:17-04:00","value":400,"type":"","binding":""},{"name":".clientdata_pixelratio","timestamp":"2019-08-05T20:30:39-04:00","value":2.625,"type":"","binding":""},{"name":".clientdata_output_bar_height","timestamp":"2019-08-05T20:30:28-04:00","value":400,"type":"","binding":""},{"name":".clientdata_output_bar_height","timestamp":"2019-08-05T20:33:36-04:00","value":400,"type":"","binding":""},{"name":".clientdata_output_bar_height","timestamp":"2019-08-05T20:35:12-04:00","value":400,"type":"","binding":""},{"name":".clientdata_output_bar_height","timestamp":"2019-08-05T20:34:00-04:00","value":400,"type":"","binding":""},{"name":".clientdata_pixelratio","timestamp":"2019-08-05T20:31:01-04:00","value":2.625,"type":"","binding":""},{"name":".clientdata_pixelratio","timestamp":"2019-08-05T20:30:53-04:00","value":2.625,"type":"","binding":""},{"name":".clientdata_output_bar_height","timestamp":"2019-08-05T20:33:33-04:00","value":400,"type":"","binding":""},{"name":".clientdata_pixelratio","timestamp":"2019-08-05T20:34:13-04:00","value":2.625,"type":"","binding":""},{"name":".clientdata_output_bar_width","timestamp":"2019-08-05T20:35:33-04:00","value":382,"type":"","binding":""},{"name":".clientdata_output_bar_height","timestamp":"2019-08-05T20:30:45-04:00","value":400,"type":"","binding":""},{"name":".clientdata_output_bar_height","timestamp":"2019-08-05T20:30:27-04:00","value":400,"type":"","binding":""},{"name":".clientdata_pixelratio","timestamp":"2019-08-05T20:35:22-04:00","value":2.625,"type":"","binding":""},{"name":".clientdata_output_bar_width","timestamp":"2019-08-05T20:30:20-04:00","value":382,"type":"","binding":""},{"name":".clientdata_output_bar_height","timestamp":"2019-08-05T20:30:24-04:00","value":400,"type":"","binding":""},{"name":".clientdata_pixelratio","timestamp":"2019-08-05T20:30:38-04:00","value":2.625,"type":"","binding":""},{"name":"sideA","timestamp":"2019-08-05T20:33:44-04:00","value":{},"type":"","binding":"shiny.selectInput"},{"name":".clientdata_pixelratio","timestamp":"2019-08-05T20:32:53-04:00","value":2.625,"type":"","binding":""},{"name":".clientdata_pixelratio","timestamp":"2019-08-05T20:33:37-04:00","value":2.625,"type":"","binding":""},{"name":".clientdata_output_bar_width","timestamp":"2019-08-05T20:30:47-04:00","value":382,"type":"","binding":""},{"name":".clientdata_output_bar_width","timestamp":"2019-08-05T20:32:42-04:00","value":382,"type":"","binding":""},{"name":".clientdata_output_bar_height","timestamp":"2019-08-05T20:36:19-04:00","value":400,"type":"","binding":""},{"name":".clientdata_pixelratio","timestamp":"2019-08-05T20:32:47-04:00","value":2.625,"type":"","binding":""},{"name":".clientdata_output_bar_height","timestamp":"2019-08-05T20:34:03-04:00","value":400,"type":"","binding":""},{"name":".clientdata_output_bar_height","timestamp":"2019-08-05T20:31:43-04:00","value":400,"type":"","binding":""},{"name":".clientdata_output_bar_height","timestamp":"2019-08-05T20:35:37-04:00","value":400,"type":"","binding":""},{"name":".clientdata_output_bar_width","timestamp":"2019-08-05T20:36:16-04:00","value":382,"type":"","binding":""},{"name":".clientdata_output_bar_height","timestamp":"2019-08-05T20:33:41-04:00","value":400,"type":"","binding":""},{"name":"slider1","timestamp":"2019-08-05T20:36:22-04:00","value":-0.024,"type":"","binding":"shiny.sliderInput"},{"name":"sideA","timestamp":"2019-08-05T20:34:04-04:00","value":["Startup Pick 1.05 | Ezekiel Elliott"],"type":"","binding":"shiny.selectInput"},{"name":".clientdata_pixelratio","timestamp":"2019-08-05T20:30:34-04:00","value":2.625,"type":"","binding":""},{"name":".clientdata_pixelratio","timestamp":"2019-08-05T20:33:54-04:00","value":2.625,"type":"","binding":""},{"name":".clientdata_output_bar_width","timestamp":"2019-08-05T20:33:37-04:00","value":382,"type":"","binding":""},{"name":".clientdata_pixelratio","timestamp":"2019-08-05T20:35:26-04:00","value":2.625,"type":"","binding":""},{"name":".clientdata_output_bar_width","timestamp":"2019-08-05T20:34:45-04:00","value":382,"type":"","binding":""},{"name":".clientdata_output_bar_width","timestamp":"2019-08-05T20:33:42-04:00","value":382,"type":"","binding":""},{"name":"sideA","timestamp":"2019-08-05T20:34:04-04:00","value":["Startup Pick 1.05 | Ezekiel Elliott"],"type":"","binding":"shiny.selectInput"},{"name":".clientdata_output_bar_height","timestamp":"2019-08-05T20:35:29-04:00","value":400,"type":"","binding":""},{"name":".clientdata_pixelratio","timestamp":"2019-08-05T20:33:39-04:00","value":2.625,"type":"","binding":""},{"name":".clientdata_output_bar_height","timestamp":"2019-08-05T20:33:52-04:00","value":400,"type":"","binding":""},{"name":".clientdata_pixelratio","timestamp":"2019-08-05T20:36:18-04:00","value":2.625,"type":"","binding":""},{"name":"sideB","timestamp":"2019-08-05T20:30:18-04:00","value":{},"type":"","binding":"shiny.selectInput"},{"name":".clientdata_pixelratio","timestamp":"2019-08-05T20:33:42-04:00","value":2.625,"type":"","binding":""},{"name":"sideA","timestamp":"2019-08-05T20:30:50-04:00","value":["Patrick Mahomes","LeVeon Bell"],"type":"","binding":"shiny.selectInput"},{"name":".clientdata_output_bar_width","timestamp":"2019-08-05T20:36:04-04:00","value":382,"type":"","binding":""},{"name":"sideA","timestamp":"2019-08-05T20:36:03-04:00","value":["Startup Pick 1.05 | Ezekiel Elliott","Startup Pick 3.05 | Dalvin Cook"],"type":"","binding":"shiny.selectInput"},{"name":".clientdata_output_bar_height","timestamp":"2019-08-05T20:36:04-04:00","value":400,"type":"","binding":""},{"name":"sideB","timestamp":"2019-08-05T20:34:04-04:00","value":["Startup Pick 1.09 | Baker Mayfield"],"type":"","binding":"shiny.selectInput"},{"name":".clientdata_output_bar_height","timestamp":"2019-08-05T20:30:42-04:00","value":400,"type":"","binding":""},{"name":".clientdata_pixelratio","timestamp":"2019-08-05T20:31:46-04:00","value":2.625,"type":"","binding":""},{"name":".clientdata_pixelratio","timestamp":"2019-08-05T20:30:19-04:00","value":2.625,"type":"","binding":""},{"name":".clientdata_output_bar_width","timestamp":"2019-08-05T20:34:53-04:00","value":382,"type":"","binding":""},{"name":".clientdata_pixelratio","timestamp":"2019-08-05T20:33:40-04:00","value":2.625,"type":"","binding":""},{"name":".clientdata_pixelratio","timestamp":"2019-08-05T20:35:46-04:00","value":2.625,"type":"","binding":""},{"name":".clientdata_output_bar_width","timestamp":"2019-08-05T20:31:21-04:00","value":382,"type":"","binding":""},{"name":".clientdata_output_bar_height","timestamp":"2019-08-05T20:34:32-04:00","value":400,"type":"","binding":""},{"name":".clientdata_output_bar_width","timestamp":"2019-08-05T20:32:36-04:00","value":382,"type":"","binding":""},{"name":".clientdata_output_bar_width","timestamp":"2019-08-05T20:35:54-04:00","value":382,"type":"","binding":""},{"name":".clientdata_output_bar_height","timestamp":"2019-08-05T20:32:36-04:00","value":400,"type":"","binding":""},{"name":".clientdata_output_bar_height","timestamp":"2019-08-05T20:36:24-04:00","value":400,"type":"","binding":""},{"name":".clientdata_output_bar_height","timestamp":"2019-08-05T20:35:36-04:00","value":400,"type":"","binding":""},{"name":".clientdata_pixelratio","timestamp":"2019-08-05T20:30:28-04:00","value":2.625,"type":"","binding":""},{"name":".clientdata_output_bar_width","timestamp":"2019-08-05T20:34:15-04:00","value":382,"type":"","binding":""},{"name":".clientdata_output_bar_width","timestamp":"2019-08-05T20:34:24-04:00","value":382,"type":"","binding":""},{"name":".clientdata_output_bar_width","timestamp":"2019-08-05T20:32:54-04:00","value":382,"type":"","binding":""},{"name":".clientdata_pixelratio","timestamp":"2019-08-05T20:35:18-04:00","value":2.625,"type":"","binding":""},{"name":".clientdata_pixelratio","timestamp":"2019-08-05T20:35:48-04:00","value":2.625,"type":"","binding":""},{"name":".clientdata_pixelratio","timestamp":"2019-08-05T20:32:36-04:00","value":2.625,"type":"","binding":""},{"name":".clientdata_output_bar_width","timestamp":"2019-08-05T20:31:28-04:00","value":382,"type":"","binding":""},{"name":".clientdata_output_bar_height","timestamp":"2019-08-05T20:34:13-04:00","value":400,"type":"","binding":""},{"name":"slider1","timestamp":"2019-08-05T20:36:16-04:00","value":-0.021,"type":"","binding":"shiny.sliderInput"},{"name":".clientdata_pixelratio","timestamp":"2019-08-05T20:32:34-04:00","value":2.625,"type":"","binding":""},{"name":"sideA","timestamp":"2019-08-05T20:33:08-04:00","value":["Patrick Mahomes","LeVeon Bell","2020 1st","Evan Engram"],"type":"","binding":"shiny.selectInput"},{"name":".clientdata_output_bar_height","timestamp":"2019-08-05T20:30:34-04:00","value":400,"type":"","binding":""},{"name":"sideA","timestamp":"2019-08-05T20:33:35-04:00","value":["2020 1st"],"type":"","binding":"shiny.selectInput"},{"name":"sideB","timestamp":"2019-08-05T20:36:04-04:00","value":["Startup Pick 1.09 | Baker Mayfield","Startup Pick 2.02 | Michael Thomas"],"type":"","binding":"shiny.selectInput"},{"name":"slider2","timestamp":"2019-08-05T20:34:02-04:00","value":0.9,"type":"","binding":"shiny.sliderInput"},{"name":".clientdata_pixelratio","timestamp":"2019-08-05T20:35:48-04:00","value":2.625,"type":"","binding":""},{"name":".clientdata_output_bar_width","timestamp":"2019-08-05T20:34:59-04:00","value":382,"type":"","binding":""},{"name":".clientdata_output_bar_width","timestamp":"2019-08-05T20:31:29-04:00","value":382,"type":"","binding":""},{"name":".clientdata_output_bar_width","timestamp":"2019-08-05T20:31:54-04:00","value":382,"type":"","binding":""},{"name":".clientdata_output_bar_height","timestamp":"2019-08-05T20:35:47-04:00","value":400,"type":"","binding":""},{"name":".clientdata_pixelratio","timestamp":"2019-08-05T20:35:29-04:00","value":2.625,"type":"","binding":""},{"name":".clientdata_output_bar_height","timestamp":"2019-08-05T20:31:29-04:00","value":400,"type":"","binding":""},{"name":"sideB","timestamp":"2019-08-05T20:36:24-04:00","value":["Startup Pick 1.09 | Baker Mayfield","Startup Pick 2.02 | Michael Thomas"],"type":"","binding":"shiny.selectInput"},{"name":".clientdata_output_bar_width","timestamp":"2019-08-05T20:34:04-04:00","value":382,"type":"","binding":""},{"name":"sideB","timestamp":"2019-08-05T20:34:53-04:00","value":["Startup Pick 1.09 | Baker Mayfield"],"type":"","binding":"shiny.selectInput"},{"name":".clientdata_pixelratio","timestamp":"2019-08-05T20:31:52-04:00","value":2.625,"type":"","binding":""},{"name":".clientdata_output_bar_height","timestamp":"2019-08-05T20:34:07-04:00","value":400,"type":"","binding":""},{"name":".clientdata_pixelratio","timestamp":"2019-08-05T20:32:40-04:00","value":2.625,"type":"","binding":""},{"name":".clientdata_output_bar_width","timestamp":"2019-08-05T20:36:23-04:00","value":382,"type":"","binding":""},{"name":".clientdata_output_bar_height","timestamp":"2019-08-05T20:35:55-04:00","value":400,"type":"","binding":""},{"name":".clientdata_output_bar_width","timestamp":"2019-08-05T20:35:12-04:00","value":382,"type":"","binding":""},{"name":"sideA","timestamp":"2019-08-05T20:33:36-04:00","value":["2020 1st"],"type":"","binding":"shiny.selectInput"},{"name":".clientdata_pixelratio","timestamp":"2019-08-05T20:30:27-04:00","value":2.625,"type":"","binding":""},{"name":".clientdata_output_bar_height","timestamp":"2019-08-05T20:33:44-04:00","value":400,"type":"","binding":""},{"name":"sideA","timestamp":"2019-08-05T20:36:04-04:00","value":["Startup Pick 1.05 | Ezekiel Elliott","Startup Pick 3.05 | Dalvin Cook"],"type":"","binding":"shiny.selectInput"},{"name":".clientdata_output_bar_width","timestamp":"2019-08-05T20:31:47-04:00","value":382,"type":"","binding":""},{"name":"sideA","timestamp":"2019-08-05T20:33:49-04:00","value":["Startup Pick 1.06 | Alvin Kamara"],"type":"","binding":"shiny.selectInput"},{"name":".clientdata_output_bar_width","timestamp":"2019-08-05T20:34:13-04:00","value":382,"type":"","binding":""},{"name":".clientdata_pixelratio","timestamp":"2019-08-05T20:36:16-04:00","value":2.625,"type":"","binding":""},{"name":".clientdata_output_bar_width","timestamp":"2019-08-05T20:34:22-04:00","value":382,"type":"","binding":""},{"name":".clientdata_pixelratio","timestamp":"2019-08-05T20:34:58-04:00","value":2.625,"type":"","binding":""},{"name":".clientdata_output_bar_height","timestamp":"2019-08-05T20:35:54-04:00","value":400,"type":"","binding":""},{"name":".clientdata_output_bar_height","timestamp":"2019-08-05T20:34:59-04:00","value":400,"type":"","binding":""},{"name":".clientdata_output_bar_height","timestamp":"2019-08-05T20:35:46-04:00","value":400,"type":"","binding":""},{"name":".clientdata_output_bar_width","timestamp":"2019-08-05T20:34:03-04:00","value":382,"type":"","binding":""},{"name":".clientdata_output_bar_height","timestamp":"2019-08-05T20:31:02-04:00","value":400,"type":"","binding":""},{"name":".clientdata_output_bar_width","timestamp":"2019-08-05T20:30:41-04:00","value":382,"type":"","binding":""},{"name":".clientdata_output_bar_height","timestamp":"2019-08-05T20:35:42-04:00","value":400,"type":"","binding":""},{"name":".clientdata_output_bar_width","timestamp":"2019-08-05T20:31:57-04:00","value":382,"type":"","binding":""},{"name":".clientdata_output_bar_height","timestamp":"2019-08-05T20:34:13-04:00","value":400,"type":"","binding":""},{"name":"sideB","timestamp":"2019-08-05T20:36:03-04:00","value":["Startup Pick 1.09 | Baker Mayfield","Startup Pick 2.02 | Michael Thomas"],"type":"","binding":"shiny.selectInput"},{"name":".clientdata_output_bar_height","timestamp":"2019-08-05T20:35:30-04:00","value":400,"type":"","binding":""},{"name":".clientdata_pixelratio","timestamp":"2019-08-05T20:31:29-04:00","value":2.625,"type":"","binding":""},{"name":".clientdata_pixelratio","timestamp":"2019-08-05T20:36:09-04:00","value":2.625,"type":"","binding":""},{"name":"sideA","timestamp":"2019-08-05T20:36:18-04:00","value":["Startup Pick 1.05 | Ezekiel Elliott","Startup Pick 3.05 | Dalvin Cook"],"type":"","binding":"shiny.selectInput"},{"name":"sideA","timestamp":"2019-08-05T20:33:52-04:00","value":["Startup Pick 1.05 | Ezekiel Elliott"],"type":"","binding":"shiny.selectInput"},{"name":"sideA","timestamp":"2019-08-05T20:33:35-04:00","value":["2020 1st"],"type":"","binding":"shiny.selectInput"},{"name":".clientdata_pixelratio","timestamp":"2019-08-05T20:30:40-04:00","value":2.625,"type":"","binding":""},{"name":".clientdata_output_bar_width","timestamp":"2019-08-05T20:31:53-04:00","value":382,"type":"","binding":""},{"name":".clientdata_pixelratio","timestamp":"2019-08-05T20:33:43-04:00","value":2.625,"type":"","binding":""},{"name":".clientdata_output_bar_height","timestamp":"2019-08-05T20:33:38-04:00","value":400,"type":"","binding":""},{"name":"sideB","timestamp":"2019-08-05T20:36:18-04:00","value":["Startup Pick 1.09 | Baker Mayfield","Startup Pick 2.02 | Michael Thomas"],"type":"","binding":"shiny.selectInput"},{"name":".clientdata_output_bar_width","timestamp":"2019-08-05T20:30:27-04:00","value":382,"type":"","binding":""},{"name":"numQB","timestamp":"2019-08-05T20:33:25-04:00","value":false,"type":"","binding":"shiny.switchInput"},{"name":".clientdata_output_bar_width","timestamp":"2019-08-05T20:35:46-04:00","value":382,"type":"","binding":""},{"name":"slider2","timestamp":"2019-08-05T20:36:00-04:00","value":0.4,"type":"","binding":"shiny.sliderInput"},{"name":".clientdata_output_bar_width","timestamp":"2019-08-05T20:31:26-04:00","value":382,"type":"","binding":""},{"name":".clientdata_output_bar_width","timestamp":"2019-08-05T20:35:23-04:00","value":382,"type":"","binding":""},{"name":".clientdata_pixelratio","timestamp":"2019-08-05T20:36:34-04:00","value":2.625,"type":"","binding":""},{"name":".clientdata_output_bar_width","timestamp":"2019-08-05T20:35:42-04:00","value":382,"type":"","binding":""},{"name":".clientdata_output_bar_height","timestamp":"2019-08-05T20:33:08-04:00","value":400,"type":"","binding":""},{"name":".clientdata_output_bar_width","timestamp":"2019-08-05T20:33:51-04:00","value":382,"type":"","binding":""},{"name":".clientdata_output_bar_height","timestamp":"2019-08-05T20:34:57-04:00","value":400,"type":"","binding":""},{"name":"numQB","timestamp":"2019-08-05T20:30:17-04:00","value":false,"type":"","binding":"shiny.switchInput"},{"name":"sideB","timestamp":"2019-08-05T20:33:32-04:00","value":{},"type":"","binding":"shiny.selectInput"},{"name":".clientdata_output_bar_width","timestamp":"2019-08-05T20:35:35-04:00","value":382,"type":"","binding":""},{"name":".clientdata_output_bar_height","timestamp":"2019-08-05T20:32:54-04:00","value":400,"type":"","binding":""},{"name":".clientdata_pixelratio","timestamp":"2019-08-05T20:33:05-04:00","value":2.625,"type":"","binding":""},{"name":".clientdata_output_bar_height","timestamp":"2019-08-05T20:31:53-04:00","value":400,"type":"","binding":""},{"name":"calcType","timestamp":"2019-08-05T20:33:34-04:00","value":"predraft","type":"","binding":"shiny.radioGroupButtonsInput"},{"name":"sideB","timestamp":"2019-08-05T20:32:32-04:00","value":["Baker Mayfield","Alvin Kamara","Mark Andrews"],"type":"","binding":"shiny.selectInput"},{"name":".clientdata_output_bar_height","timestamp":"2019-08-05T20:33:49-04:00","value":400,"type":"","binding":""},{"name":".clientdata_pixelratio","timestamp":"2019-08-05T20:35:47-04:00","value":2.625,"type":"","binding":""},{"name":".clientdata_output_bar_width","timestamp":"2019-08-05T20:36:28-04:00","value":382,"type":"","binding":""},{"name":"sideB","timestamp":"2019-08-05T20:33:08-04:00","value":["Baker Mayfield","Alvin Kamara","Mark Andrews"],"type":"","binding":"shiny.selectInput"},{"name":".clientdata_pixelratio","timestamp":"2019-08-05T20:34:38-04:00","value":2.625,"type":"","binding":""},{"name":".clientdata_output_bar_height","timestamp":"2019-08-05T20:34:04-04:00","value":400,"type":"","binding":""},{"name":"sideA","timestamp":"2019-08-05T20:36:03-04:00","value":["Startup Pick 1.05 | Ezekiel Elliott","Startup Pick 3.05 | Dalvin Cook"],"type":"","binding":"shiny.selectInput"},{"name":".clientdata_output_bar_height","timestamp":"2019-08-05T20:35:09-04:00","value":400,"type":"","binding":""},{"name":"numQB","timestamp":"2019-08-05T20:33:06-04:00","value":true,"type":"","binding":"shiny.switchInput"},{"name":".clientdata_output_bar_width","timestamp":"2019-08-05T20:34:57-04:00","value":382,"type":"","binding":""},{"name":".clientdata_output_bar_height","timestamp":"2019-08-05T20:31:01-04:00","value":400,"type":"","binding":""},{"name":"sideB","timestamp":"2019-08-05T20:33:08-04:00","value":["Baker Mayfield","Alvin Kamara","Mark Andrews"],"type":"","binding":"shiny.selectInput"},{"name":"sideB","timestamp":"2019-08-05T20:33:27-04:00","value":["Baker Mayfield","Alvin Kamara","Mark Andrews"],"type":"","binding":"shiny.selectInput"},{"name":".clientdata_output_bar_width","timestamp":"2019-08-05T20:33:49-04:00","value":382,"type":"","binding":""},{"name":"sideA","timestamp":"2019-08-05T20:36:01-04:00","value":["Startup Pick 1.05 | Ezekiel Elliott","Startup Pick 3.05 | Dalvin Cook"],"type":"","binding":"shiny.selectInput"},{"name":".clientdata_pixelratio","timestamp":"2019-08-05T20:35:12-04:00","value":2.625,"type":"","binding":""},{"name":".clientdata_output_bar_height","timestamp":"2019-08-05T20:32:34-04:00","value":400,"type":"","binding":""},{"name":".clientdata_pixelratio","timestamp":"2019-08-05T20:31:03-04:00","value":2.625,"type":"","binding":""},{"name":".clientdata_pixelratio","timestamp":"2019-08-05T20:36:16-04:00","value":2.625,"type":"","binding":""},{"name":".clientdata_pixelratio","timestamp":"2019-08-05T20:31:21-04:00","value":2.625,"type":"","binding":""},{"name":".clientdata_pixelratio","timestamp":"2019-08-05T20:30:46-04:00","value":2.625,"type":"","binding":""},{"name":".clientdata_pixelratio","timestamp":"2019-08-05T20:35:54-04:00","value":2.625,"type":"","binding":""},{"name":".clientdata_pixelratio","timestamp":"2019-08-05T20:34:43-04:00","value":2.625,"type":"","binding":""},{"name":".clientdata_pixelratio","timestamp":"2019-08-05T20:34:52-04:00","value":2.625,"type":"","binding":""},{"name":"sideA","timestamp":"2019-08-05T20:33:27-04:00","value":["Patrick Mahomes","LeVeon Bell","2020 1st","Evan Engram"],"type":"","binding":"shiny.selectInput"},{"name":".clientdata_output_bar_width","timestamp":"2019-08-05T20:30:55-04:00","value":382,"type":"","binding":""},{"name":".clientdata_pixelratio","timestamp":"2019-08-05T20:30:39-04:00","value":2.625,"type":"","binding":""},{"name":".clientdata_output_bar_height","timestamp":"2019-08-05T20:33:32-04:00","value":400,"type":"","binding":""},{"name":".clientdata_output_bar_width","timestamp":"2019-08-05T20:35:45-04:00","value":382,"type":"","binding":""},{"name":".clientdata_output_bar_width","timestamp":"2019-08-05T20:36:24-04:00","value":382,"type":"","binding":""},{"name":".clientdata_pixelratio","timestamp":"2019-08-05T20:31:42-04:00","value":2.625,"type":"","binding":""},{"name":".clientdata_pixelratio","timestamp":"2019-08-05T20:34:02-04:00","value":2.625,"type":"","binding":""},{"name":"sideB","timestamp":"2019-08-05T20:36:24-04:00","value":["Startup Pick 1.09 | Baker Mayfield","Startup Pick 2.02 | Michael Thomas"],"type":"","binding":"shiny.selectInput"},{"name":".clientdata_pixelratio","timestamp":"2019-08-05T20:34:23-04:00","value":2.625,"type":"","binding":""},{"name":".clientdata_pixelratio","timestamp":"2019-08-05T20:35:35-04:00","value":2.625,"type":"","binding":""},{"name":".clientdata_output_bar_height","timestamp":"2019-08-05T20:35:45-04:00","value":400,"type":"","binding":""},{"name":"sideA","timestamp":"2019-08-05T20:34:49-04:00","value":["Startup Pick 1.05 | Ezekiel Elliott","Startup Pick 3.05 | Dalvin Cook"],"type":"","binding":"shiny.selectInput"},{"name":"sideA","timestamp":"2019-08-05T20:33:08-04:00","value":["Patrick Mahomes","LeVeon Bell","2020 1st","Evan Engram"],"type":"","binding":"shiny.selectInput"},{"name":".clientdata_output_bar_width","timestamp":"2019-08-05T20:33:06-04:00","value":382,"type":"","binding":""},{"name":".clientdata_output_bar_width","timestamp":"2019-08-05T20:35:55-04:00","value":382,"type":"","binding":""},{"name":"sideA","timestamp":"2019-08-05T20:31:24-04:00","value":["Patrick Mahomes","LeVeon Bell","2020 1st"],"type":"","binding":"shiny.selectInput"},{"name":".clientdata_pixelratio","timestamp":"2019-08-05T20:33:41-04:00","value":2.625,"type":"","binding":""},{"name":".clientdata_pixelratio","timestamp":"2019-08-05T20:33:55-04:00","value":2.625,"type":"","binding":""},{"name":".clientdata_output_bar_width","timestamp":"2019-08-05T20:33:40-04:00","value":382,"type":"","binding":""},{"name":"sideA","timestamp":"2019-08-05T20:33:40-04:00","value":["2020 1st"],"type":"","binding":"shiny.selectInput"},{"name":".clientdata_output_bar_width","timestamp":"2019-08-05T20:33:25-04:00","value":382,"type":"","binding":""},{"name":".clientdata_output_bar_height","timestamp":"2019-08-05T20:32:49-04:00","value":400,"type":"","binding":""},{"name":".clientdata_output_bar_width","timestamp":"2019-08-05T20:36:01-04:00","value":382,"type":"","binding":""},{"name":".clientdata_output_bar_width","timestamp":"2019-08-05T20:30:16-04:00","value":382,"type":"","binding":""},{"name":"sideB","timestamp":"2019-08-05T20:36:23-04:00","value":["Startup Pick 1.09 | Baker Mayfield","Startup Pick 2.02 | Michael Thomas"],"type":"","binding":"shiny.selectInput"},{"name":".clientdata_output_bar_height","timestamp":"2019-08-05T20:33:35-04:00","value":400,"type":"","binding":""},{"name":"sideA","timestamp":"2019-08-05T20:34:43-04:00","value":["Startup Pick 1.05 | Ezekiel Elliott"],"type":"","binding":"shiny.selectInput"},{"name":".clientdata_output_bar_width","timestamp":"2019-08-05T20:31:04-04:00","value":382,"type":"","binding":""},{"name":".clientdata_output_bar_height","timestamp":"2019-08-05T20:32:53-04:00","value":400,"type":"","binding":""},{"name":".clientdata_output_bar_width","timestamp":"2019-08-05T20:36:34-04:00","value":382,"type":"","binding":""},{"name":".clientdata_output_bar_height","timestamp":"2019-08-05T20:31:26-04:00","value":400,"type":"","binding":""},{"name":".clientdata_output_bar_width","timestamp":"2019-08-05T20:34:32-04:00","value":382,"type":"","binding":""},{"name":"sideA","timestamp":"2019-08-05T20:33:40-04:00","value":["2020 1st"],"type":"","binding":"shiny.selectInput"},{"name":".clientdata_output_bar_width","timestamp":"2019-08-05T20:32:56-04:00","value":382,"type":"","binding":""},{"name":"sideA","timestamp":"2019-08-05T20:36:18-04:00","value":["Startup Pick 1.05 | Ezekiel Elliott","Startup Pick 3.05 | Dalvin Cook"],"type":"","binding":"shiny.selectInput"},{"name":".clientdata_output_bar_height","timestamp":"2019-08-05T20:31:47-04:00","value":400,"type":"","binding":""},{"name":".clientdata_output_bar_width","timestamp":"2019-08-05T20:33:27-04:00","value":382,"type":"","binding":""},{"name":".clientdata_output_bar_width","timestamp":"2019-08-05T20:31:01-04:00","value":382,"type":"","binding":""},{"name":".clientdata_output_bar_height","timestamp":"2019-08-05T20:31:21-04:00","value":400,"type":"","binding":""},{"name":".clientdata_output_bar_width","timestamp":"2019-08-05T20:32:49-04:00","value":382,"type":"","binding":""},{"name":".clientdata_output_bar_width","timestamp":"2019-08-05T20:35:37-04:00","value":382,"type":"","binding":""},{"name":".clientdata_output_bar_height","timestamp":"2019-08-05T20:30:53-04:00","value":400,"type":"","binding":""},{"name":".clientdata_pixelratio","timestamp":"2019-08-05T20:32:53-04:00","value":2.625,"type":"","binding":""},{"name":".clientdata_output_bar_width","timestamp":"2019-08-05T20:31:51-04:00","value":382,"type":"","binding":""},{"name":".clientdata_output_bar_height","timestamp":"2019-08-05T20:32:48-04:00","value":400,"type":"","binding":""},{"name":".clientdata_output_bar_height","timestamp":"2019-08-05T20:33:44-04:00","value":400,"type":"","binding":""},{"name":".clientdata_pixelratio","timestamp":"2019-08-05T20:34:08-04:00","value":2.625,"type":"","binding":""},{"name":".clientdata_output_bar_height","timestamp":"2019-08-05T20:35:35-04:00","value":400,"type":"","binding":""},{"name":".clientdata_output_bar_height","timestamp":"2019-08-05T20:30:47-04:00","value":400,"type":"","binding":""},{"name":"calcType","timestamp":"2019-08-05T20:33:36-04:00","value":"predraft","type":"","binding":"shiny.radioGroupButtonsInput"},{"name":".clientdata_pixelratio","timestamp":"2019-08-05T20:31:02-04:00","value":2.625,"type":"","binding":""},{"name":"sideB","timestamp":"2019-08-05T20:34:04-04:00","value":["Startup Pick 1.09 | Baker Mayfield"],"type":"","binding":"shiny.selectInput"},{"name":"sideB","timestamp":"2019-08-05T20:33:27-04:00","value":["Baker Mayfield","Alvin Kamara","Mark Andrews"],"type":"","binding":"shiny.selectInput"},{"name":".clientdata_output_bar_width","timestamp":"2019-08-05T20:35:36-04:00","value":382,"type":"","binding":""},{"name":".clientdata_output_bar_width","timestamp":"2019-08-05T20:36:03-04:00","value":382,"type":"","binding":""},{"name":".clientdata_output_bar_height","timestamp":"2019-08-05T20:36:18-04:00","value":400,"type":"","binding":""},{"name":".clientdata_output_bar_width","timestamp":"2019-08-05T20:32:34-04:00","value":382,"type":"","binding":""},{"name":"sideA","timestamp":"2019-08-05T20:33:36-04:00","value":["2020 1st"],"type":"","binding":"shiny.selectInput"},{"name":".clientdata_output_bar_width","timestamp":"2019-08-05T20:34:41-04:00","value":382,"type":"","binding":""},{"name":".clientdata_output_bar_width","timestamp":"2019-08-05T20:33:08-04:00","value":382,"type":"","binding":""},{"name":"sideA","timestamp":"2019-08-05T20:36:22-04:00","value":["Startup Pick 1.05 | Ezekiel Elliott","Startup Pick 3.05 | Dalvin Cook"],"type":"","binding":"shiny.selectInput"},{"name":".clientdata_output_bar_height","timestamp":"2019-08-05T20:34:39-04:00","value":400,"type":"","binding":""},{"name":".clientdata_pixelratio","timestamp":"2019-08-05T20:35:33-04:00","value":2.625,"type":"","binding":""},{"name":".clientdata_output_bar_width","timestamp":"2019-08-05T20:30:18-04:00","value":382,"type":"","binding":""},{"name":".clientdata_output_bar_height","timestamp":"2019-08-05T20:30:18-04:00","value":400,"type":"","binding":""},{"name":".clientdata_pixelratio","timestamp":"2019-08-05T20:35:41-04:00","value":2.625,"type":"","binding":""},{"name":".clientdata_output_bar_height","timestamp":"2019-08-05T20:34:58-04:00","value":400,"type":"","binding":""},{"name":".clientdata_output_bar_width","timestamp":"2019-08-05T20:30:34-04:00","value":382,"type":"","binding":""},{"name":".clientdata_output_bar_height","timestamp":"2019-08-05T20:33:06-04:00","value":400,"type":"","binding":""},{"name":".clientdata_output_bar_width","timestamp":"2019-08-05T20:30:33-04:00","value":382,"type":"","binding":""},{"name":".clientdata_pixelratio","timestamp":"2019-08-05T20:34:14-04:00","value":2.625,"type":"","binding":""},{"name":"sideA","timestamp":"2019-08-05T20:36:24-04:00","value":["Startup Pick 1.05 | Ezekiel Elliott","Startup Pick 3.05 | Dalvin Cook"],"type":"","binding":"shiny.selectInput"},{"name":".clientdata_output_bar_height","timestamp":"2019-08-05T20:34:41-04:00","value":400,"type":"","binding":""},{"name":".clientdata_output_bar_height","timestamp":"2019-08-05T20:34:54-04:00","value":400,"type":"","binding":""},{"name":".clientdata_output_bar_width","timestamp":"2019-08-05T20:34:54-04:00","value":382,"type":"","binding":""},{"name":".clientdata_output_bar_height","timestamp":"2019-08-05T20:36:16-04:00","value":400,"type":"","binding":""},{"name":".clientdata_output_bar_height","timestamp":"2019-08-05T20:31:28-04:00","value":400,"type":"","binding":""},{"name":".clientdata_output_bar_height","timestamp":"2019-08-05T20:30:41-04:00","value":400,"type":"","binding":""},{"name":".clientdata_output_bar_width","timestamp":"2019-08-05T20:30:51-04:00","value":382,"type":"","binding":""},{"name":".clientdata_output_bar_width","timestamp":"2019-08-05T20:33:00-04:00","value":382,"type":"","binding":""},{"name":".clientdata_pixelratio","timestamp":"2019-08-05T20:33:38-04:00","value":2.625,"type":"","binding":""},{"name":".clientdata_output_bar_height","timestamp":"2019-08-05T20:31:51-04:00","value":400,"type":"","binding":""},{"name":"sideB","timestamp":"2019-08-05T20:36:04-04:00","value":["Startup Pick 1.09 | Baker Mayfield","Startup Pick 2.02 | Michael Thomas"],"type":"","binding":"shiny.selectInput"},{"name":"sideA","timestamp":"2019-08-05T20:33:32-04:00","value":["2020 1st"],"type":"","binding":"shiny.selectInput"},{"name":".clientdata_pixelratio","timestamp":"2019-08-05T20:30:41-04:00","value":2.625,"type":"","binding":""},{"name":".clientdata_output_bar_height","timestamp":"2019-08-05T20:35:48-04:00","value":400,"type":"","binding":""},{"name":"sideA","timestamp":"2019-08-05T20:33:51-04:00","value":{},"type":"","binding":"shiny.selectInput"},{"name":".clientdata_pixelratio","timestamp":"2019-08-05T20:35:44-04:00","value":2.625,"type":"","binding":""},{"name":".clientdata_output_bar_width","timestamp":"2019-08-05T20:32:48-04:00","value":382,"type":"","binding":""},{"name":"sideA","timestamp":"2019-08-05T20:31:50-04:00","value":["Patrick Mahomes","LeVeon Bell","2020 1st","Evan Engram"],"type":"","binding":"shiny.selectInput"},{"name":".clientdata_output_bar_height","timestamp":"2019-08-05T20:35:27-04:00","value":400,"type":"","binding":""},{"name":".clientdata_output_bar_width","timestamp":"2019-08-05T20:34:00-04:00","value":382,"type":"","binding":""},{"name":".clientdata_pixelratio","timestamp":"2019-08-05T20:35:28-04:00","value":2.625,"type":"","binding":""},{"name":".clientdata_output_bar_height","timestamp":"2019-08-05T20:36:34-04:00","value":400,"type":"","binding":""},{"name":".clientdata_pixelratio","timestamp":"2019-08-05T20:35:22-04:00","value":2.625,"type":"","binding":""},{"name":"sideA","timestamp":"2019-08-05T20:34:12-04:00","value":["Startup Pick 1.05 | Ezekiel Elliott","Startup Pick 2.02 | Michael Thomas"],"type":"","binding":"shiny.selectInput"},{"name":"sideA","timestamp":"2019-08-05T20:30:18-04:00","value":{},"type":"","binding":"shiny.selectInput"},{"name":".clientdata_output_bar_height","timestamp":"2019-08-05T20:33:27-04:00","value":400,"type":"","binding":""},{"name":".clientdata_output_bar_width","timestamp":"2019-08-05T20:33:44-04:00","value":382,"type":"","binding":""},{"name":".clientdata_output_bar_height","timestamp":"2019-08-05T20:33:51-04:00","value":400,"type":"","binding":""},{"name":".clientdata_output_bar_height","timestamp":"2019-08-05T20:33:25-04:00","value":400,"type":"","binding":""},{"name":"sideB","timestamp":"2019-08-05T20:33:37-04:00","value":{},"type":"","binding":"shiny.selectInput"},{"name":".clientdata_output_bar_width","timestamp":"2019-08-05T20:32:41-04:00","value":382,"type":"","binding":""},{"name":"sideB","timestamp":"2019-08-05T20:34:56-04:00","value":["Startup Pick 1.09 | Baker Mayfield","Startup Pick 2.02 | Michael Thomas"],"type":"","binding":"shiny.selectInput"},{"name":".clientdata_pixelratio","timestamp":"2019-08-05T20:30:41-04:00","value":2.625,"type":"","binding":""},{"name":".clientdata_pixelratio","timestamp":"2019-08-05T20:32:55-04:00","value":2.625,"type":"","binding":""},{"name":".clientdata_output_bar_width","timestamp":"2019-08-05T20:34:51-04:00","value":382,"type":"","binding":""},{"name":".clientdata_output_bar_width","timestamp":"2019-08-05T20:34:13-04:00","value":382,"type":"","binding":""},{"name":".clientdata_output_bar_height","timestamp":"2019-08-05T20:33:42-04:00","value":400,"type":"","binding":""},{"name":".clientdata_output_bar_height","timestamp":"2019-08-05T20:31:00-04:00","value":400,"type":"","binding":""},{"name":".clientdata_output_bar_width","timestamp":"2019-08-05T20:35:27-04:00","value":382,"type":"","binding":""},{"name":".clientdata_output_bar_height","timestamp":"2019-08-05T20:30:33-04:00","value":400,"type":"","binding":""},{"name":".clientdata_output_bar_height","timestamp":"2019-08-05T20:35:33-04:00","value":400,"type":"","binding":""},{"name":".clientdata_output_bar_width","timestamp":"2019-08-05T20:33:36-04:00","value":382,"type":"","binding":""},{"name":".clientdata_output_bar_width","timestamp":"2019-08-05T20:33:44-04:00","value":382,"type":"","binding":""},{"name":".clientdata_pixelratio","timestamp":"2019-08-05T20:36:18-04:00","value":2.625,"type":"","binding":""},{"name":".clientdata_output_bar_width","timestamp":"2019-08-05T20:36:17-04:00","value":382,"type":"","binding":""},{"name":".clientdata_output_bar_width","timestamp":"2019-08-05T20:36:18-04:00","value":382,"type":"","binding":""},{"name":".clientdata_output_bar_height","timestamp":"2019-08-05T20:30:20-04:00","value":400,"type":"","binding":""},{"name":".clientdata_output_bar_height","timestamp":"2019-08-05T20:32:33-04:00","value":400,"type":"","binding":""},{"name":".clientdata_output_bar_width","timestamp":"2019-08-05T20:32:53-04:00","value":382,"type":"","binding":""},{"name":"sideA","timestamp":"2019-08-05T20:33:37-04:00","value":["2020 1st"],"type":"","binding":"shiny.selectInput"},{"name":".clientdata_output_bar_height","timestamp":"2019-08-05T20:32:42-04:00","value":400,"type":"","binding":""},{"name":".clientdata_output_bar_height","timestamp":"2019-08-05T20:31:46-04:00","value":400,"type":"","binding":""},{"name":"sideB","timestamp":"2019-08-05T20:33:41-04:00","value":{},"type":"","binding":"shiny.selectInput"},{"name":".clientdata_output_bar_height","timestamp":"2019-08-05T20:35:23-04:00","value":400,"type":"","binding":""},{"name":".clientdata_output_bar_height","timestamp":"2019-08-05T20:30:55-04:00","value":400,"type":"","binding":""},{"name":".clientdata_pixelratio","timestamp":"2019-08-05T20:33:25-04:00","value":2.625,"type":"","binding":""},{"name":".clientdata_output_bar_width","timestamp":"2019-08-05T20:36:10-04:00","value":382,"type":"","binding":""},{"name":".clientdata_pixelratio","timestamp":"2019-08-05T20:30:40-04:00","value":2.625,"type":"","binding":""},{"name":".clientdata_pixelratio","timestamp":"2019-08-05T20:30:39-04:00","value":2.625,"type":"","binding":""},{"name":".clientdata_output_bar_width","timestamp":"2019-08-05T20:32:45-04:00","value":382,"type":"","binding":""},{"name":".clientdata_output_bar_width","timestamp":"2019-08-05T20:34:43-04:00","value":382,"type":"","binding":""},{"name":".clientdata_output_bar_height","timestamp":"2019-08-05T20:33:00-04:00","value":400,"type":"","binding":""},{"name":".clientdata_output_bar_width","timestamp":"2019-08-05T20:33:56-04:00","value":382,"type":"","binding":""},{"name":".clientdata_output_bar_height","timestamp":"2019-08-05T20:36:10-04:00","value":400,"type":"","binding":""},{"name":".clientdata_pixelratio","timestamp":"2019-08-05T20:35:09-04:00","value":2.625,"type":"","binding":""},{"name":".clientdata_output_bar_width","timestamp":"2019-08-05T20:31:55-04:00","value":382,"type":"","binding":""},{"name":".clientdata_pixelratio","timestamp":"2019-08-05T20:34:22-04:00","value":2.625,"type":"","binding":""},{"name":".clientdata_output_bar_height","timestamp":"2019-08-05T20:33:37-04:00","value":400,"type":"","binding":""},{"name":".clientdata_output_bar_width","timestamp":"2019-08-05T20:33:52-04:00","value":382,"type":"","binding":""}],"errors":[{"name":"diffTable","timestamp":"2019-08-05T20:33:51-04:00","error":""},{"name":"tableB","timestamp":"2019-08-05T20:33:33-04:00","error":""},{"name":"winRange","timestamp":"2019-08-05T20:33:44-04:00","error":""},{"name":"winner","timestamp":"2019-08-05T20:33:33-04:00","error":""},{"name":"tableText","timestamp":"2019-08-05T20:33:44-04:00","error":""},{"name":"bar","timestamp":"2019-08-05T20:33:52-04:00","error":""},{"name":"winRange","timestamp":"2019-08-05T20:33:49-04:00","error":""},{"name":"bar","timestamp":"2019-08-05T20:33:44-04:00","error":""},{"name":"bar","timestamp":"2019-08-05T20:33:32-04:00","error":"An error has occurred. Check your logs or contact the app author for clarification."},{"name":"winner","timestamp":"2019-08-05T20:33:49-04:00","error":""},{"name":"tableText","timestamp":"2019-08-05T20:33:51-04:00","error":""},{"name":"winner","timestamp":"2019-08-05T20:33:52-04:00","error":""},{"name":"winner","timestamp":"2019-08-05T20:33:51-04:00","error":""},{"name":"winner","timestamp":"2019-08-05T20:30:24-04:00","error":""},{"name":"bar","timestamp":"2019-08-05T20:33:49-04:00","error":""},{"name":"bar","timestamp":"2019-08-05T20:33:51-04:00","error":""},{"name":"tableA","timestamp":"2019-08-05T20:33:44-04:00","error":""},{"name":"winRange","timestamp":"2019-08-05T20:33:51-04:00","error":""},{"name":"winRange","timestamp":"2019-08-05T20:33:33-04:00","error":""},{"name":"tableA","timestamp":"2019-08-05T20:33:51-04:00","error":""},{"name":"bar","timestamp":"2019-08-05T20:33:33-04:00","error":""},{"name":"diffTable","timestamp":"2019-08-05T20:33:44-04:00","error":""},{"name":"winner","timestamp":"2019-08-05T20:33:44-04:00","error":""},{"name":"winRange","timestamp":"2019-08-05T20:30:24-04:00","error":""},{"name":"bar","timestamp":"2019-08-05T20:30:24-04:00","error":""},{"name":"winRange","timestamp":"2019-08-05T20:33:52-04:00","error":""}],"outputs":[{"name":"tableA","timestamp":"2019-08-05T20:33:33-04:00","binding":"shiny.htmlOutput"},{"name":"textA","timestamp":"2019-08-05T20:36:03-04:00","binding":"shiny.textOutput"},{"name":"textB","timestamp":"2019-08-05T20:33:32-04:00","binding":"shiny.textOutput"},{"name":"tableText","timestamp":"2019-08-05T20:30:51-04:00","binding":"shiny.textOutput"},{"name":"textB","timestamp":"2019-08-05T20:36:03-04:00","binding":"shiny.textOutput"},{"name":"textB","timestamp":"2019-08-05T20:33:37-04:00","binding":"shiny.textOutput"},{"name":"winner","timestamp":"2019-08-05T20:34:04-04:00","binding":"shiny.textOutput"},{"name":"bar","timestamp":"2019-08-05T20:36:22-04:00","binding":"shiny.imageOutput"},{"name":"diffTable","timestamp":"2019-08-05T20:36:03-04:00","binding":"shiny.htmlOutput"},{"name":"textB","timestamp":"2019-08-05T20:33:35-04:00","binding":"shiny.textOutput"},{"name":"textB","timestamp":"2019-08-05T20:32:33-04:00","binding":"shiny.textOutput"},{"name":"bar","timestamp":"2019-08-05T20:34:13-04:00","binding":"shiny.imageOutput"},{"name":"diffTable","timestamp":"2019-08-05T20:33:35-04:00","binding":"shiny.htmlOutput"},{"name":"bar","timestamp":"2019-08-05T20:33:27-04:00","binding":"shiny.imageOutput"},{"name":"tableText","timestamp":"2019-08-05T20:33:33-04:00","binding":"shiny.textOutput"},{"name":"diffTable","timestamp":"2019-08-05T20:32:33-04:00","binding":"shiny.htmlOutput"},{"name":"diffTable","timestamp":"2019-08-05T20:33:33-04:00","binding":"shiny.htmlOutput"},{"name":"tableText","timestamp":"2019-08-05T20:31:51-04:00","binding":"shiny.textOutput"},{"name":"bar","timestamp":"2019-08-05T20:31:26-04:00","binding":"shiny.imageOutput"},{"name":"tableA","timestamp":"2019-08-05T20:34:51-04:00","binding":"shiny.htmlOutput"},{"name":"tableA","timestamp":"2019-08-05T20:33:40-04:00","binding":"shiny.htmlOutput"},{"name":"tableA","timestamp":"2019-08-05T20:33:07-04:00","binding":"shiny.htmlOutput"},{"name":"tableA","timestamp":"2019-08-05T20:36:03-04:00","binding":"shiny.htmlOutput"},{"name":"winRange","timestamp":"2019-08-05T20:36:18-04:00","binding":"shiny.textOutput"},{"name":"diffTable","timestamp":"2019-08-05T20:31:00-04:00","binding":"shiny.htmlOutput"},{"name":"diffTable","timestamp":"2019-08-05T20:30:51-04:00","binding":"shiny.htmlOutput"},{"name":"textA","timestamp":"2019-08-05T20:33:35-04:00","binding":"shiny.textOutput"},{"name":"tableB","timestamp":"2019-08-05T20:34:54-04:00","binding":"shiny.htmlOutput"},{"name":"textB","timestamp":"2019-08-05T20:34:54-04:00","binding":"shiny.textOutput"},{"name":"diffTable","timestamp":"2019-08-05T20:34:45-04:00","binding":"shiny.htmlOutput"},{"name":"textA","timestamp":"2019-08-05T20:33:37-04:00","binding":"shiny.textOutput"},{"name":"tableA","timestamp":"2019-08-05T20:31:26-04:00","binding":"shiny.htmlOutput"},{"name":"bar","timestamp":"2019-08-05T20:34:45-04:00","binding":"shiny.imageOutput"},{"name":"bar","timestamp":"2019-08-05T20:36:03-04:00","binding":"shiny.imageOutput"},{"name":"tableA","timestamp":"2019-08-05T20:33:49-04:00","binding":"shiny.htmlOutput"},{"name":"winner","timestamp":"2019-08-05T20:34:00-04:00","binding":"shiny.textOutput"},{"name":"winRange","timestamp":"2019-08-05T20:32:33-04:00","binding":"shiny.textOutput"},{"name":"tableA","timestamp":"2019-08-05T20:33:27-04:00","binding":"shiny.htmlOutput"},{"name":"tableA","timestamp":"2019-08-05T20:30:51-04:00","binding":"shiny.htmlOutput"},{"name":"diffTable","timestamp":"2019-08-05T20:36:18-04:00","binding":"shiny.htmlOutput"},{"name":"winner","timestamp":"2019-08-05T20:31:51-04:00","binding":"shiny.textOutput"},{"name":"textA","timestamp":"2019-08-05T20:34:51-04:00","binding":"shiny.textOutput"},{"name":"winner","timestamp":"2019-08-05T20:34:54-04:00","binding":"shiny.textOutput"},{"name":"textA","timestamp":"2019-08-05T20:30:18-04:00","binding":"shiny.textOutput"},{"name":"tableA","timestamp":"2019-08-05T20:33:35-04:00","binding":"shiny.htmlOutput"},{"name":"tableB","timestamp":"2019-08-05T20:36:18-04:00","binding":"shiny.htmlOutput"},{"name":"winRange","timestamp":"2019-08-05T20:33:07-04:00","binding":"shiny.textOutput"},{"name":"tableText","timestamp":"2019-08-05T20:33:49-04:00","binding":"shiny.textOutput"},{"name":"textA","timestamp":"2019-08-05T20:36:01-04:00","binding":"shiny.textOutput"},{"name":"tableA","timestamp":"2019-08-05T20:33:32-04:00","binding":"shiny.htmlOutput"},{"name":"bar","timestamp":"2019-08-05T20:36:01-04:00","binding":"shiny.imageOutput"},{"name":"tableB","timestamp":"2019-08-05T20:36:03-04:00","binding":"shiny.htmlOutput"},{"name":"textA","timestamp":"2019-08-05T20:31:51-04:00","binding":"shiny.textOutput"},{"name":"winner","timestamp":"2019-08-05T20:34:22-04:00","binding":"shiny.textOutput"},{"name":"tableB","timestamp":"2019-08-05T20:33:27-04:00","binding":"shiny.htmlOutput"},{"name":"textA","timestamp":"2019-08-05T20:34:45-04:00","binding":"shiny.textOutput"},{"name":"tableA","timestamp":"2019-08-05T20:36:03-04:00","binding":"shiny.htmlOutput"},{"name":"diffTable","timestamp":"2019-08-05T20:31:26-04:00","binding":"shiny.htmlOutput"},{"name":"diffTable","timestamp":"2019-08-05T20:34:04-04:00","binding":"shiny.htmlOutput"},{"name":"bar","timestamp":"2019-08-05T20:32:33-04:00","binding":"shiny.imageOutput"},{"name":"diffTable","timestamp":"2019-08-05T20:33:37-04:00","binding":"shiny.htmlOutput"},{"name":"diffTable","timestamp":"2019-08-05T20:36:01-04:00","binding":"shiny.htmlOutput"},{"name":"winner","timestamp":"2019-08-05T20:36:01-04:00","binding":"shiny.textOutput"},{"name":"tableA","timestamp":"2019-08-05T20:36:24-04:00","binding":"shiny.htmlOutput"},{"name":"textA","timestamp":"2019-08-05T20:30:24-04:00","binding":"shiny.textOutput"},{"name":"textA","timestamp":"2019-08-05T20:30:51-04:00","binding":"shiny.textOutput"},{"name":"textA","timestamp":"2019-08-05T20:31:26-04:00","binding":"shiny.textOutput"},{"name":"textB","timestamp":"2019-08-05T20:31:00-04:00","binding":"shiny.textOutput"},{"name":"textA","timestamp":"2019-08-05T20:33:40-04:00","binding":"shiny.textOutput"},{"name":"winner","timestamp":"2019-08-05T20:30:51-04:00","binding":"shiny.textOutput"},{"name":"textA","timestamp":"2019-08-05T20:33:35-04:00","binding":"shiny.textOutput"},{"name":"tableA","timestamp":"2019-08-05T20:33:52-04:00","binding":"shiny.htmlOutput"},{"name":"diffTable","timestamp":"2019-08-05T20:34:13-04:00","binding":"shiny.htmlOutput"},{"name":"winRange","timestamp":"2019-08-05T20:33:27-04:00","binding":"shiny.textOutput"},{"name":"diffTable","timestamp":"2019-08-05T20:33:49-04:00","binding":"shiny.htmlOutput"},{"name":"winRange","timestamp":"2019-08-05T20:34:57-04:00","binding":"shiny.textOutput"},{"name":"textB","timestamp":"2019-08-05T20:34:22-04:00","binding":"shiny.textOutput"},{"name":"winner","timestamp":"2019-08-05T20:33:27-04:00","binding":"shiny.textOutput"},{"name":"winner","timestamp":"2019-08-05T20:34:13-04:00","binding":"shiny.textOutput"},{"name":"textA","timestamp":"2019-08-05T20:33:32-04:00","binding":"shiny.textOutput"},{"name":"winner","timestamp":"2019-08-05T20:36:18-04:00","binding":"shiny.textOutput"},{"name":"tableB","timestamp":"2019-08-05T20:32:33-04:00","binding":"shiny.htmlOutput"},{"name":"bar","timestamp":"2019-08-05T20:33:07-04:00","binding":"shiny.imageOutput"},{"name":"winner","timestamp":"2019-08-05T20:33:07-04:00","binding":"shiny.textOutput"},{"name":"winner","timestamp":"2019-08-05T20:36:03-04:00","binding":"shiny.textOutput"},{"name":"tableA","timestamp":"2019-08-05T20:36:01-04:00","binding":"shiny.htmlOutput"},{"name":"tableText","timestamp":"2019-08-05T20:34:13-04:00","binding":"shiny.textOutput"},{"name":"winner","timestamp":"2019-08-05T20:34:57-04:00","binding":"shiny.textOutput"},{"name":"tableB","timestamp":"2019-08-05T20:33:32-04:00","binding":"shiny.htmlOutput"},{"name":"tableB","timestamp":"2019-08-05T20:34:00-04:00","binding":"shiny.htmlOutput"},{"name":"tableA","timestamp":"2019-08-05T20:36:18-04:00","binding":"shiny.htmlOutput"},{"name":"bar","timestamp":"2019-08-05T20:34:57-04:00","binding":"shiny.imageOutput"},{"name":"diffTable","timestamp":"2019-08-05T20:36:24-04:00","binding":"shiny.htmlOutput"},{"name":"diffTable","timestamp":"2019-08-05T20:33:32-04:00","binding":"shiny.htmlOutput"},{"name":"textB","timestamp":"2019-08-05T20:34:57-04:00","binding":"shiny.textOutput"},{"name":"winRange","timestamp":"2019-08-05T20:30:32-04:00","binding":"shiny.textOutput"},{"name":"diffTable","timestamp":"2019-08-05T20:33:27-04:00","binding":"shiny.htmlOutput"},{"name":"winRange","timestamp":"2019-08-05T20:34:51-04:00","binding":"shiny.textOutput"},{"name":"bar","timestamp":"2019-08-05T20:34:51-04:00","binding":"shiny.imageOutput"},{"name":"textA","timestamp":"2019-08-05T20:33:27-04:00","binding":"shiny.textOutput"},{"name":"winner","timestamp":"2019-08-05T20:36:03-04:00","binding":"shiny.textOutput"},{"name":"tableB","timestamp":"2019-08-05T20:31:00-04:00","binding":"shiny.htmlOutput"},{"name":"textA","timestamp":"2019-08-05T20:36:22-04:00","binding":"shiny.textOutput"},{"name":"textB","timestamp":"2019-08-05T20:30:18-04:00","binding":"shiny.textOutput"},{"name":"tableB","timestamp":"2019-08-05T20:36:01-04:00","binding":"shiny.htmlOutput"},{"name":"textA","timestamp":"2019-08-05T20:33:44-04:00","binding":"shiny.textOutput"},{"name":"tableA","timestamp":"2019-08-05T20:33:35-04:00","binding":"shiny.htmlOutput"},{"name":"winRange","timestamp":"2019-08-05T20:30:51-04:00","binding":"shiny.textOutput"},{"name":"winner","timestamp":"2019-08-05T20:34:51-04:00","binding":"shiny.textOutput"},{"name":"diffTable","timestamp":"2019-08-05T20:36:22-04:00","binding":"shiny.htmlOutput"},{"name":"textA","timestamp":"2019-08-05T20:33:52-04:00","binding":"shiny.textOutput"},{"name":"winner","timestamp":"2019-08-05T20:36:24-04:00","binding":"shiny.textOutput"},{"name":"bar","timestamp":"2019-08-05T20:36:03-04:00","binding":"shiny.imageOutput"},{"name":"textB","timestamp":"2019-08-05T20:33:33-04:00","binding":"shiny.textOutput"},{"name":"tableA","timestamp":"2019-08-05T20:31:51-04:00","binding":"shiny.htmlOutput"},{"name":"winRange","timestamp":"2019-08-05T20:31:26-04:00","binding":"shiny.textOutput"},{"name":"winRange","timestamp":"2019-08-05T20:34:00-04:00","binding":"shiny.textOutput"},{"name":"winner","timestamp":"2019-08-05T20:31:26-04:00","binding":"shiny.textOutput"},{"name":"tableText","timestamp":"2019-08-05T20:33:52-04:00","binding":"shiny.textOutput"},{"name":"textB","timestamp":"2019-08-05T20:34:04-04:00","binding":"shiny.textOutput"},{"name":"diffTable","timestamp":"2019-08-05T20:34:57-04:00","binding":"shiny.htmlOutput"},{"name":"winRange","timestamp":"2019-08-05T20:36:24-04:00","binding":"shiny.textOutput"},{"name":"tableA","timestamp":"2019-08-05T20:30:24-04:00","binding":"shiny.htmlOutput"},{"name":"bar","timestamp":"2019-08-05T20:31:51-04:00","binding":"shiny.imageOutput"},{"name":"textB","timestamp":"2019-08-05T20:33:40-04:00","binding":"shiny.textOutput"},{"name":"bar","timestamp":"2019-08-05T20:34:00-04:00","binding":"shiny.imageOutput"},{"name":"textA","timestamp":"2019-08-05T20:36:24-04:00","binding":"shiny.textOutput"},{"name":"diffTable","timestamp":"2019-08-05T20:33:35-04:00","binding":"shiny.htmlOutput"},{"name":"tableA","timestamp":"2019-08-05T20:33:37-04:00","binding":"shiny.htmlOutput"},{"name":"winRange","timestamp":"2019-08-05T20:36:03-04:00","binding":"shiny.textOutput"},{"name":"winRange","timestamp":"2019-08-05T20:31:51-04:00","binding":"shiny.textOutput"},{"name":"tableA","timestamp":"2019-08-05T20:34:04-04:00","binding":"shiny.htmlOutput"},{"name":"diffTable","timestamp":"2019-08-05T20:30:24-04:00","binding":"shiny.htmlOutput"},{"name":"diffTable","timestamp":"2019-08-05T20:34:00-04:00","binding":"shiny.htmlOutput"},{"name":"textB","timestamp":"2019-08-05T20:36:01-04:00","binding":"shiny.textOutput"},{"name":"bar","timestamp":"2019-08-05T20:36:18-04:00","binding":"shiny.imageOutput"},{"name":"winRange","timestamp":"2019-08-05T20:36:22-04:00","binding":"shiny.textOutput"},{"name":"winner","timestamp":"2019-08-05T20:34:45-04:00","binding":"shiny.textOutput"},{"name":"tableText","timestamp":"2019-08-05T20:34:51-04:00","binding":"shiny.textOutput"},{"name":"diffTable","timestamp":"2019-08-05T20:31:51-04:00","binding":"shiny.htmlOutput"},{"name":"winRange","timestamp":"2019-08-05T20:36:01-04:00","binding":"shiny.textOutput"},{"name":"winRange","timestamp":"2019-08-05T20:34:04-04:00","binding":"shiny.textOutput"},{"name":"diffTable","timestamp":"2019-08-05T20:34:54-04:00","binding":"shiny.htmlOutput"},{"name":"textA","timestamp":"2019-08-05T20:33:07-04:00","binding":"shiny.textOutput"},{"name":"tableText","timestamp":"2019-08-05T20:31:26-04:00","binding":"shiny.textOutput"},{"name":"diffTable","timestamp":"2019-08-05T20:33:40-04:00","binding":"shiny.htmlOutput"},{"name":"tableText","timestamp":"2019-08-05T20:30:24-04:00","binding":"shiny.textOutput"},{"name":"textB","timestamp":"2019-08-05T20:33:27-04:00","binding":"shiny.textOutput"},{"name":"tableB","timestamp":"2019-08-05T20:30:32-04:00","binding":"shiny.htmlOutput"},{"name":"textB","timestamp":"2019-08-05T20:33:35-04:00","binding":"shiny.textOutput"},{"name":"diffTable","timestamp":"2019-08-05T20:36:03-04:00","binding":"shiny.htmlOutput"},{"name":"textB","timestamp":"2019-08-05T20:36:03-04:00","binding":"shiny.textOutput"},{"name":"textB","timestamp":"2019-08-05T20:33:07-04:00","binding":"shiny.textOutput"},{"name":"tableB","timestamp":"2019-08-05T20:34:57-04:00","binding":"shiny.htmlOutput"},{"name":"bar","timestamp":"2019-08-05T20:34:54-04:00","binding":"shiny.imageOutput"},{"name":"winner","timestamp":"2019-08-05T20:33:32-04:00","binding":"shiny.textOutput"},{"name":"diffTable","timestamp":"2019-08-05T20:33:52-04:00","binding":"shiny.htmlOutput"},{"name":"tableB","timestamp":"2019-08-05T20:34:04-04:00","binding":"shiny.htmlOutput"},{"name":"tableB","timestamp":"2019-08-05T20:33:07-04:00","binding":"shiny.htmlOutput"},{"name":"tableB","timestamp":"2019-08-05T20:36:24-04:00","binding":"shiny.htmlOutput"},{"name":"bar","timestamp":"2019-08-05T20:31:00-04:00","binding":"shiny.imageOutput"},{"name":"diffTable","timestamp":"2019-08-05T20:33:07-04:00","binding":"shiny.htmlOutput"},{"name":"bar","timestamp":"2019-08-05T20:34:04-04:00","binding":"shiny.imageOutput"},{"name":"textB","timestamp":"2019-08-05T20:30:32-04:00","binding":"shiny.textOutput"},{"name":"winner","timestamp":"2019-08-05T20:36:22-04:00","binding":"shiny.textOutput"},{"name":"winRange","timestamp":"2019-08-05T20:34:54-04:00","binding":"shiny.textOutput"},{"name":"winner","timestamp":"2019-08-05T20:30:32-04:00","binding":"shiny.textOutput"},{"name":"winRange","timestamp":"2019-08-05T20:33:32-04:00","binding":"shiny.textOutput"},{"name":"textA","timestamp":"2019-08-05T20:36:18-04:00","binding":"shiny.textOutput"},{"name":"tableA","timestamp":"2019-08-05T20:36:22-04:00","binding":"shiny.htmlOutput"},{"name":"winRange","timestamp":"2019-08-05T20:34:13-04:00","binding":"shiny.textOutput"},{"name":"diffTable","timestamp":"2019-08-05T20:34:51-04:00","binding":"shiny.htmlOutput"},{"name":"tableB","timestamp":"2019-08-05T20:36:22-04:00","binding":"shiny.htmlOutput"},{"name":"winner","timestamp":"2019-08-05T20:31:00-04:00","binding":"shiny.textOutput"},{"name":"winRange","timestamp":"2019-08-05T20:34:45-04:00","binding":"shiny.textOutput"},{"name":"diffTable","timestamp":"2019-08-05T20:30:32-04:00","binding":"shiny.htmlOutput"},{"name":"tableB","timestamp":"2019-08-05T20:36:03-04:00","binding":"shiny.htmlOutput"},{"name":"tableA","timestamp":"2019-08-05T20:34:13-04:00","binding":"shiny.htmlOutput"},{"name":"textA","timestamp":"2019-08-05T20:34:04-04:00","binding":"shiny.textOutput"},{"name":"winRange","timestamp":"2019-08-05T20:31:00-04:00","binding":"shiny.textOutput"},{"name":"textA","timestamp":"2019-08-05T20:33:33-04:00","binding":"shiny.textOutput"},{"name":"diffTable","timestamp":"2019-08-05T20:34:22-04:00","binding":"shiny.htmlOutput"},{"name":"textA","timestamp":"2019-08-05T20:36:03-04:00","binding":"shiny.textOutput"},{"name":"bar","timestamp":"2019-08-05T20:36:24-04:00","binding":"shiny.imageOutput"},{"name":"bar","timestamp":"2019-08-05T20:30:32-04:00","binding":"shiny.imageOutput"},{"name":"textB","timestamp":"2019-08-05T20:36:18-04:00","binding":"shiny.textOutput"},{"name":"textB","timestamp":"2019-08-05T20:36:24-04:00","binding":"shiny.textOutput"},{"name":"winRange","timestamp":"2019-08-05T20:36:03-04:00","binding":"shiny.textOutput"},{"name":"tableB","timestamp":"2019-08-05T20:34:22-04:00","binding":"shiny.htmlOutput"},{"name":"bar","timestamp":"2019-08-05T20:30:51-04:00","binding":"shiny.imageOutput"},{"name":"textB","timestamp":"2019-08-05T20:34:00-04:00","binding":"shiny.textOutput"},{"name":"bar","timestamp":"2019-08-05T20:34:22-04:00","binding":"shiny.imageOutput"},{"name":"textA","timestamp":"2019-08-05T20:34:13-04:00","binding":"shiny.textOutput"},{"name":"tableA","timestamp":"2019-08-05T20:34:45-04:00","binding":"shiny.htmlOutput"},{"name":"winRange","timestamp":"2019-08-05T20:34:22-04:00","binding":"shiny.textOutput"},{"name":"textA","timestamp":"2019-08-05T20:33:49-04:00","binding":"shiny.textOutput"},{"name":"winner","timestamp":"2019-08-05T20:32:33-04:00","binding":"shiny.textOutput"},{"name":"textA","timestamp":"2019-08-05T20:33:51-04:00","binding":"shiny.textOutput"},{"name":"tableText","timestamp":"2019-08-05T20:34:45-04:00","binding":"shiny.textOutput"},{"name":"textB","timestamp":"2019-08-05T20:36:22-04:00","binding":"shiny.textOutput"}],"session":[{"app":"calculator","user":"shiny","server_connected":"2019-08-06T00:30:16+0000","sessionid":"08ac8272d6c230c9478f31d0fea22ead","server_disconnected":"2019-08-06T00:43:44+0000"}]}
