{"inputs":[{"name":"sideB","timestamp":"2019-08-07T21:20:27-04:00","value":["Cooper Kupp"],"type":"","binding":"shiny.selectInput"},{"name":"sideB","timestamp":"2019-08-07T21:21:07-04:00","value":["Cooper Kupp"],"type":"","binding":"shiny.selectInput"},{"name":".clientdata_output_bar_width","timestamp":"2019-08-07T21:20:28-04:00","value":345,"type":"","binding":""},{"name":".clientdata_output_bar_height","timestamp":"2019-08-07T21:20:17-04:00","value":400,"type":"","binding":""},{"name":"sideB","timestamp":"2019-08-07T21:20:41-04:00","value":["Cooper Kupp","Julian Edelman"],"type":"","binding":"shiny.selectInput"},{"name":"sideB","timestamp":"2019-08-07T21:19:59-04:00","value":{},"type":"","binding":"shiny.selectInput"},{"name":".clientdata_output_bar_width","timestamp":"2019-08-07T21:20:08-04:00","value":345,"type":"","binding":""},{"name":"numQB","timestamp":"2019-08-07T21:19:58-04:00","value":false,"type":"","binding":"shiny.switchInput"},{"name":"sideB","timestamp":"2019-08-07T21:21:00-04:00","value":["Cooper Kupp","Miles Sanders"],"type":"","binding":"shiny.selectInput"},{"name":"sideB","timestamp":"2019-08-07T21:20:17-04:00","value":["Cooper Kupp","Kalen Ballage"],"type":"","binding":"shiny.selectInput"},{"name":".clientdata_output_bar_width","timestamp":"2019-08-07T21:20:15-04:00","value":345,"type":"","binding":""},{"name":".clientdata_pixelratio","timestamp":"2019-08-07T21:21:01-04:00","value":2,"type":"","binding":""},{"name":"sideA","timestamp":"2019-08-07T21:19:58-04:00","value":{},"type":"","binding":"shiny.selectInput"},{"name":"sideB","timestamp":"2019-08-07T21:19:58-04:00","value":{},"type":"","binding":"shiny.selectInput"},{"name":"sideA","timestamp":"2019-08-07T21:20:06-04:00","value":["LeVeon Bell"],"type":"","binding":"shiny.selectInput"},{"name":".clientdata_output_bar_height","timestamp":"2019-08-07T21:20:07-04:00","value":400,"type":"","binding":""},{"name":"leagueSize","timestamp":"2019-08-07T21:20:01-04:00","value":"10","type":"","binding":"shiny.selectInput"},{"name":".clientdata_output_bar_width","timestamp":"2019-08-07T21:21:08-04:00","value":345,"type":"","binding":""},{"name":".clientdata_output_bar_height","timestamp":"2019-08-07T21:20:58-04:00","value":400,"type":"","binding":""},{"name":"sideB","timestamp":"2019-08-07T21:19:57-04:00","value":{},"type":"","binding":"shiny.selectInput"},{"name":".clientdata_output_bar_height","timestamp":"2019-08-07T21:20:08-04:00","value":400,"type":"","binding":""},{"name":"sideB","timestamp":"2019-08-07T21:20:14-04:00","value":["Cooper Kupp"],"type":"","binding":"shiny.selectInput"},{"name":".clientdata_output_bar_width","timestamp":"2019-08-07T21:20:58-04:00","value":345,"type":"","binding":""},{"name":".clientdata_output_bar_width","timestamp":"2019-08-07T21:21:00-04:00","value":345,"type":"","binding":""},{"name":".clientdata_output_bar_width","timestamp":"2019-08-07T21:21:02-04:00","value":345,"type":"","binding":""},{"name":".clientdata_output_bar_height","timestamp":"2019-08-07T21:20:54-04:00","value":400,"type":"","binding":""},{"name":".clientdata_output_bar_height","timestamp":"2019-08-07T21:20:15-04:00","value":400,"type":"","binding":""},{"name":".clientdata_output_bar_width","timestamp":"2019-08-07T21:20:07-04:00","value":345,"type":"","binding":""},{"name":".clientdata_output_bar_height","timestamp":"2019-08-07T21:19:57-04:00","value":400,"type":"","binding":""},{"name":".clientdata_output_bar_width","timestamp":"2019-08-07T21:21:09-04:00","value":345,"type":"","binding":""},{"name":"sideA","timestamp":"2019-08-07T21:19:59-04:00","value":{},"type":"","binding":"shiny.selectInput"},{"name":".clientdata_output_bar_height","timestamp":"2019-08-07T21:20:41-04:00","value":400,"type":"","binding":""},{"name":".clientdata_output_bar_width","timestamp":"2019-08-07T21:20:41-04:00","value":345,"type":"","binding":""},{"name":"sideA","timestamp":"2019-08-07T21:20:01-04:00","value":{},"type":"","binding":"shiny.selectInput"},{"name":"sideB","timestamp":"2019-08-07T21:20:57-04:00","value":["Cooper Kupp"],"type":"","binding":"shiny.selectInput"},{"name":"sideB","timestamp":"2019-08-07T21:21:09-04:00","value":{},"type":"","binding":"shiny.selectInput"},{"name":"sideB","timestamp":"2019-08-07T21:20:02-04:00","value":{},"type":"","binding":"shiny.selectInput"},{"name":"numQB","timestamp":"2019-08-07T21:19:57-04:00","value":true,"type":"","binding":"shiny.switchInput"},{"name":".clientdata_output_bar_width","timestamp":"2019-08-07T21:20:54-04:00","value":345,"type":"","binding":""},{"name":".clientdata_output_bar_width","timestamp":"2019-08-07T21:19:59-04:00","value":345,"type":"","binding":""},{"name":".clientdata_output_bar_height","timestamp":"2019-08-07T21:20:28-04:00","value":400,"type":"","binding":""},{"name":".clientdata_output_bar_width","timestamp":"2019-08-07T21:19:57-04:00","value":345,"type":"","binding":""},{"name":".clientdata_output_bar_height","timestamp":"2019-08-07T21:21:09-04:00","value":400,"type":"","binding":""},{"name":".clientdata_pixelratio","timestamp":"2019-08-07T21:20:53-04:00","value":2,"type":"","binding":""},{"name":"sideA","timestamp":"2019-08-07T21:19:57-04:00","value":{},"type":"","binding":"shiny.selectInput"},{"name":".clientdata_output_bar_height","timestamp":"2019-08-07T21:20:09-04:00","value":400,"type":"","binding":""},{"name":".clientdata_output_bar_height","timestamp":"2019-08-07T21:19:59-04:00","value":400,"type":"","binding":""},{"name":"sideA","timestamp":"2019-08-07T21:20:08-04:00","value":["LeVeon Bell"],"type":"","binding":"shiny.selectInput"},{"name":".clientdata_output_bar_width","timestamp":"2019-08-07T21:20:09-04:00","value":345,"type":"","binding":""},{"name":".clientdata_output_bar_height","timestamp":"2019-08-07T21:21:02-04:00","value":400,"type":"","binding":""},{"name":".clientdata_output_bar_width","timestamp":"2019-08-07T21:20:17-04:00","value":345,"type":"","binding":""},{"name":".clientdata_output_bar_height","timestamp":"2019-08-07T21:21:00-04:00","value":400,"type":"","binding":""},{"name":".clientdata_output_bar_height","timestamp":"2019-08-07T21:21:08-04:00","value":400,"type":"","binding":""},{"name":".clientdata_pixelratio","timestamp":"2019-08-07T21:19:58-04:00","value":2,"type":"","binding":""},{"name":"sideA","timestamp":"2019-08-07T21:20:07-04:00","value":["LeVeon Bell","Antonio Gates"],"type":"","binding":"shiny.selectInput"}],"errors":[{"name":"bar","timestamp":"2019-08-07T21:20:07-04:00","error":""},{"name":"winRange","timestamp":"2019-08-07T21:20:07-04:00","error":""},{"name":"bar","timestamp":"2019-08-07T21:21:09-04:00","error":""},{"name":"winner","timestamp":"2019-08-07T21:20:07-04:00","error":""},{"name":"winRange","timestamp":"2019-08-07T21:21:09-04:00","error":""},{"name":"winRange","timestamp":"2019-08-07T21:20:08-04:00","error":""},{"name":"winner","timestamp":"2019-08-07T21:20:08-04:00","error":""},{"name":"bar","timestamp":"2019-08-07T21:20:09-04:00","error":""},{"name":"winRange","timestamp":"2019-08-07T21:20:09-04:00","error":""},{"name":"tableB","timestamp":"2019-08-07T21:21:09-04:00","error":""},{"name":"winner","timestamp":"2019-08-07T21:21:09-04:00","error":""},{"name":"bar","timestamp":"2019-08-07T21:20:08-04:00","error":""},{"name":"winner","timestamp":"2019-08-07T21:20:09-04:00","error":""}],"outputs":[{"name":"diffTable","timestamp":"2019-08-07T21:20:58-04:00","binding":"shiny.htmlOutput"},{"name":"textA","timestamp":"2019-08-07T21:19:58-04:00","binding":"shiny.textOutput"},{"name":"textB","timestamp":"2019-08-07T21:21:00-04:00","binding":"shiny.textOutput"},{"name":"diffTable","timestamp":"2019-08-07T21:20:07-04:00","binding":"shiny.htmlOutput"},{"name":"textB","timestamp":"2019-08-07T21:20:01-04:00","binding":"shiny.textOutput"},{"name":"diffTable","timestamp":"2019-08-07T21:20:08-04:00","binding":"shiny.htmlOutput"},{"name":"textB","timestamp":"2019-08-07T21:20:17-04:00","binding":"shiny.textOutput"},{"name":"bar","timestamp":"2019-08-07T21:20:15-04:00","binding":"shiny.imageOutput"},{"name":"textB","timestamp":"2019-08-07T21:20:28-04:00","binding":"shiny.textOutput"},{"name":"diffTable","timestamp":"2019-08-07T21:20:09-04:00","binding":"shiny.htmlOutput"},{"name":"tableB","timestamp":"2019-08-07T21:20:28-04:00","binding":"shiny.htmlOutput"},{"name":"winRange","timestamp":"2019-08-07T21:20:41-04:00","binding":"shiny.textOutput"},{"name":"textA","timestamp":"2019-08-07T21:20:07-04:00","binding":"shiny.textOutput"},{"name":"tableText","timestamp":"2019-08-07T21:20:07-04:00","binding":"shiny.textOutput"},{"name":"tableB","timestamp":"2019-08-07T21:20:17-04:00","binding":"shiny.htmlOutput"},{"name":"bar","timestamp":"2019-08-07T21:21:08-04:00","binding":"shiny.imageOutput"},{"name":"textB","timestamp":"2019-08-07T21:20:15-04:00","binding":"shiny.textOutput"},{"name":"diffTable","timestamp":"2019-08-07T21:20:28-04:00","binding":"shiny.htmlOutput"},{"name":"textA","timestamp":"2019-08-07T21:20:08-04:00","binding":"shiny.textOutput"},{"name":"winner","timestamp":"2019-08-07T21:21:08-04:00","binding":"shiny.textOutput"},{"name":"diffTable","timestamp":"2019-08-07T21:20:41-04:00","binding":"shiny.htmlOutput"},{"name":"winner","timestamp":"2019-08-07T21:20:28-04:00","binding":"shiny.textOutput"},{"name":"winner","timestamp":"2019-08-07T21:21:00-04:00","binding":"shiny.textOutput"},{"name":"diffTable","timestamp":"2019-08-07T21:21:09-04:00","binding":"shiny.htmlOutput"},{"name":"winner","timestamp":"2019-08-07T21:20:41-04:00","binding":"shiny.textOutput"},{"name":"tableB","timestamp":"2019-08-07T21:21:00-04:00","binding":"shiny.htmlOutput"},{"name":"winner","timestamp":"2019-08-07T21:20:17-04:00","binding":"shiny.textOutput"},{"name":"textA","timestamp":"2019-08-07T21:20:09-04:00","binding":"shiny.textOutput"},{"name":"bar","timestamp":"2019-08-07T21:21:00-04:00","binding":"shiny.imageOutput"},{"name":"textB","timestamp":"2019-08-07T21:21:09-04:00","binding":"shiny.textOutput"},{"name":"bar","timestamp":"2019-08-07T21:20:28-04:00","binding":"shiny.imageOutput"},{"name":"textB","timestamp":"2019-08-07T21:19:59-04:00","binding":"shiny.textOutput"},{"name":"diffTable","timestamp":"2019-08-07T21:20:17-04:00","binding":"shiny.htmlOutput"},{"name":"winRange","timestamp":"2019-08-07T21:20:17-04:00","binding":"shiny.textOutput"},{"name":"textB","timestamp":"2019-08-07T21:20:41-04:00","binding":"shiny.textOutput"},{"name":"tableB","timestamp":"2019-08-07T21:21:08-04:00","binding":"shiny.htmlOutput"},{"name":"tableB","timestamp":"2019-08-07T21:20:58-04:00","binding":"shiny.htmlOutput"},{"name":"tableText","timestamp":"2019-08-07T21:20:09-04:00","binding":"shiny.textOutput"},{"name":"textB","timestamp":"2019-08-07T21:21:08-04:00","binding":"shiny.textOutput"},{"name":"winner","timestamp":"2019-08-07T21:20:15-04:00","binding":"shiny.textOutput"},{"name":"winRange","timestamp":"2019-08-07T21:20:28-04:00","binding":"shiny.textOutput"},{"name":"tableA","timestamp":"2019-08-07T21:20:08-04:00","binding":"shiny.htmlOutput"},{"name":"winRange","timestamp":"2019-08-07T21:21:08-04:00","binding":"shiny.textOutput"},{"name":"bar","timestamp":"2019-08-07T21:20:17-04:00","binding":"shiny.imageOutput"},{"name":"textA","timestamp":"2019-08-07T21:20:01-04:00","binding":"shiny.textOutput"},{"name":"tableA","timestamp":"2019-08-07T21:20:07-04:00","binding":"shiny.htmlOutput"},{"name":"tableB","timestamp":"2019-08-07T21:20:41-04:00","binding":"shiny.htmlOutput"},{"name":"textB","timestamp":"2019-08-07T21:19:58-04:00","binding":"shiny.textOutput"},{"name":"textB","timestamp":"2019-08-07T21:19:57-04:00","binding":"shiny.textOutput"},{"name":"winner","timestamp":"2019-08-07T21:20:58-04:00","binding":"shiny.textOutput"},{"name":"winRange","timestamp":"2019-08-07T21:20:58-04:00","binding":"shiny.textOutput"},{"name":"bar","timestamp":"2019-08-07T21:20:58-04:00","binding":"shiny.imageOutput"},{"name":"diffTable","timestamp":"2019-08-07T21:20:15-04:00","binding":"shiny.htmlOutput"},{"name":"textB","timestamp":"2019-08-07T21:20:58-04:00","binding":"shiny.textOutput"},{"name":"tableB","timestamp":"2019-08-07T21:20:15-04:00","binding":"shiny.htmlOutput"},{"name":"diffTable","timestamp":"2019-08-07T21:21:08-04:00","binding":"shiny.htmlOutput"},{"name":"tableText","timestamp":"2019-08-07T21:20:08-04:00","binding":"shiny.textOutput"},{"name":"winRange","timestamp":"2019-08-07T21:20:15-04:00","binding":"shiny.textOutput"},{"name":"bar","timestamp":"2019-08-07T21:20:41-04:00","binding":"shiny.imageOutput"},{"name":"tableA","timestamp":"2019-08-07T21:20:09-04:00","binding":"shiny.htmlOutput"},{"name":"textA","timestamp":"2019-08-07T21:19:57-04:00","binding":"shiny.textOutput"},{"name":"diffTable","timestamp":"2019-08-07T21:21:00-04:00","binding":"shiny.htmlOutput"},{"name":"winRange","timestamp":"2019-08-07T21:21:00-04:00","binding":"shiny.textOutput"},{"name":"textA","timestamp":"2019-08-07T21:19:59-04:00","binding":"shiny.textOutput"}],"session":[{"app":"calculator","user":"shiny","server_connected":"2019-08-08T01:19:56+0000","sessionid":"d214ea75d49692734189e13ead8017ff","server_disconnected":"2019-08-08T01:22:01+0000"}]}
