{"inputs":[{"name":".clientdata_output_bar_width","timestamp":"2019-08-01T22:18:23-05:00","value":330,"type":"","binding":""},{"name":".clientdata_output_bar_width","timestamp":"2019-08-01T22:18:34-05:00","value":330,"type":"","binding":""},{"name":".clientdata_output_bar_width","timestamp":"2019-08-01T22:18:15-05:00","value":330,"type":"","binding":""},{"name":".clientdata_output_bar_height","timestamp":"2019-08-01T22:18:24-05:00","value":400,"type":"","binding":""},{"name":"numQB","timestamp":"2019-08-01T22:18:18-05:00","value":true,"type":"","binding":"shiny.switchInput"},{"name":"sideA","timestamp":"2019-08-01T22:18:21-05:00","value":{},"type":"","binding":"shiny.selectInput"},{"name":".clientdata_pixelratio","timestamp":"2019-08-01T22:18:33-05:00","value":3,"type":"","binding":""},{"name":"sideA","timestamp":"2019-08-01T22:18:16-05:00","value":{},"type":"","binding":"shiny.selectInput"},{"name":"sideB","timestamp":"2019-08-01T22:18:20-05:00","value":{},"type":"","binding":"shiny.selectInput"},{"name":"sideA","timestamp":"2019-08-01T22:18:18-05:00","value":{},"type":"","binding":"shiny.selectInput"},{"name":".clientdata_output_bar_height","timestamp":"2019-08-01T22:18:23-05:00","value":400,"type":"","binding":""},{"name":".clientdata_output_bar_width","timestamp":"2019-08-01T22:18:24-05:00","value":330,"type":"","binding":""},{"name":"sideB","timestamp":"2019-08-01T22:18:16-05:00","value":{},"type":"","binding":"shiny.selectInput"},{"name":".clientdata_output_bar_width","timestamp":"2019-08-01T22:18:31-05:00","value":330,"type":"","binding":""},{"name":".clientdata_pixelratio","timestamp":"2019-08-01T22:18:24-05:00","value":3,"type":"","binding":""},{"name":"sideB","timestamp":"2019-08-01T22:18:21-05:00","value":{},"type":"","binding":"shiny.selectInput"},{"name":".clientdata_output_bar_width","timestamp":"2019-08-01T22:18:33-05:00","value":330,"type":"","binding":""},{"name":".clientdata_output_bar_height","timestamp":"2019-08-01T22:18:31-05:00","value":400,"type":"","binding":""},{"name":".clientdata_pixelratio","timestamp":"2019-08-01T22:18:31-05:00","value":3,"type":"","binding":""},{"name":".clientdata_pixelratio","timestamp":"2019-08-01T22:18:22-05:00","value":3,"type":"","binding":""},{"name":".clientdata_output_bar_height","timestamp":"2019-08-01T22:18:15-05:00","value":400,"type":"","binding":""},{"name":".clientdata_pixelratio","timestamp":"2019-08-01T22:18:22-05:00","value":3,"type":"","binding":""},{"name":"numQB","timestamp":"2019-08-01T22:18:16-05:00","value":false,"type":"","binding":"shiny.switchInput"},{"name":"sideA","timestamp":"2019-08-01T22:18:20-05:00","value":{},"type":"","binding":"shiny.selectInput"},{"name":".clientdata_output_bar_height","timestamp":"2019-08-01T22:18:34-05:00","value":400,"type":"","binding":""},{"name":".clientdata_pixelratio","timestamp":"2019-08-01T22:18:24-05:00","value":3,"type":"","binding":""},{"name":"sideB","timestamp":"2019-08-01T22:18:19-05:00","value":{},"type":"","binding":"shiny.selectInput"},{"name":"numQB","timestamp":"2019-08-01T22:18:19-05:00","value":false,"type":"","binding":"shiny.switchInput"},{"name":".clientdata_output_bar_height","timestamp":"2019-08-01T22:18:33-05:00","value":400,"type":"","binding":""},{"name":".clientdata_pixelratio","timestamp":"2019-08-01T22:18:35-05:00","value":3,"type":"","binding":""},{"name":".clientdata_pixelratio","timestamp":"2019-08-01T22:18:34-05:00","value":3,"type":"","binding":""},{"name":"numQB","timestamp":"2019-08-01T22:18:20-05:00","value":true,"type":"","binding":"shiny.switchInput"}],"outputs":[{"name":"textB","timestamp":"2019-08-01T22:18:16-05:00","binding":"shiny.textOutput"},{"name":"textA","timestamp":"2019-08-01T22:18:20-05:00","binding":"shiny.textOutput"},{"name":"textB","timestamp":"2019-08-01T22:18:21-05:00","binding":"shiny.textOutput"},{"name":"textB","timestamp":"2019-08-01T22:18:18-05:00","binding":"shiny.textOutput"},{"name":"textA","timestamp":"2019-08-01T22:18:21-05:00","binding":"shiny.textOutput"},{"name":"textA","timestamp":"2019-08-01T22:18:16-05:00","binding":"shiny.textOutput"},{"name":"textB","timestamp":"2019-08-01T22:18:20-05:00","binding":"shiny.textOutput"},{"name":"textA","timestamp":"2019-08-01T22:18:18-05:00","binding":"shiny.textOutput"}],"session":[{"app":"calculator","user":"shiny","server_connected":"2019-08-02T03:18:14+0000","sessionid":"29a0fe7439c9b8de4eaf42044087191d","server_disconnected":"2019-08-02T03:18:50+0000"}]}
